{"WordData":[{"Id":"airport","Active":"1","Text":"AIRPORT","DrawingId":"airport","Value":"","SortValue":"","Drawing":"1E82","Kind":"Noun","Category":"City","PlaySessionLink":"","Tags":"","Complexity":"7","Gender":"","Form":"","Article":"","LinkedWord":"","Notes":"","Spanish":"AEROPUERTO","Italian":"AEROPORTO"},{"Id":"apple","Active":"1","Text":"APPLE","DrawingId":"apple","Value":"","SortValue":"","Drawing":"42","Kind":"Noun","Category":"Food","PlaySessionLink":"","Tags":"food","Complexity":"5","Gender":"","Form":"Singular","Article":"","LinkedWord":"","Notes":"","Spanish":"MANZANA","Italian":"MELA"},{"Id":"apricot","Active":"1","Text":"APRICOT","DrawingId":"apricot","Value":"","SortValue":"","Drawing":"43","Kind":"Noun","Category":"Food","PlaySessionLink":"","Tags":"food","Complexity":"7","Gender":"","Form":"","Article":"","LinkedWord":"","Notes":"","Spanish":"DAMASCO","Italian":"ALBICOCCA"},{"Id":"arm","Active":"1","Text":"ARM","DrawingId":"arm","Value":"","SortValue":"","Drawing":"116","Kind":"Noun","Category":"Body","PlaySessionLink":"","Tags":"","Complexity":"3","Gender":"","Form":"","Article":"","LinkedWord":"","Notes":"","Spanish":"BRAZO","Italian":"BRACCIO"},{"Id":"aunt","Active":"1","Text":"AUNT","DrawingId":"aunt","Value":"","SortValue":"","Drawing":"A1","Kind":"Noun","Category":"Family","PlaySessionLink":"","Tags":"","Complexity":"4","Gender":"","Form":"","Article":"","LinkedWord":"","Notes":"","Spanish":"TÍA","Italian":"ZIA"},{"Id":"autumn","Active":"1","Text":"AUTUMN","DrawingId":"autumn","Value":"3","SortValue":"3","Drawing":"7B","Kind":"Noun","Category":"Seasons","PlaySessionLink":"","Tags":"","Complexity":"6","Gender":"","Form":"","Article":"","LinkedWord":"","Notes":"","Spanish":"OTOÑO","Italian":"AUTUNNO"},{"Id":"back","Active":"1","Text":"BACK","DrawingId":"back","Value":"","SortValue":"","Drawing":"45","Kind":"Noun","Category":"Body","PlaySessionLink":"","Tags":"","Complexity":"4","Gender":"","Form":"","Article":"","LinkedWord":"","Notes":"","Spanish":"ESPALDA","Italian":"SCHIENA"},{"Id":"ball","Active":"1","Text":"BALL","DrawingId":"ball","Value":"","SortValue":"","Drawing":"A3","Kind":"Noun","Category":"Objects","PlaySessionLink":"","Tags":"","Complexity":"4","Gender":"","Form":"","Article":"","LinkedWord":"","Notes":"","Spanish":"PELOTA","Italian":"PALLA"},{"Id":"banana","Active":"1","Text":"BANANA","DrawingId":"banana","Value":"","SortValue":"","Drawing":"46","Kind":"Noun","Category":"Food","PlaySessionLink":"","Tags":"","Complexity":"6","Gender":"","Form":"Singular","Article":"","LinkedWord":"","Notes":"","Spanish":"BANANA","Italian":"BANANA"},{"Id":"bank","Active":"1","Text":"BANK","DrawingId":"bank","Value":"","SortValue":"","Drawing":"47","Kind":"Noun","Category":"City","PlaySessionLink":"","Tags":"","Complexity":"4","Gender":"","Form":"","Article":"","LinkedWord":"","Notes":"","Spanish":"BANCO","Italian":"BANCA"},{"Id":"beach","Active":"1","Text":"BEACH","DrawingId":"beach","Value":"","SortValue":"","Drawing":"1E83","Kind":"Noun","Category":"Nature","PlaySessionLink":"","Tags":"","Complexity":"5","Gender":"","Form":"","Article":"","LinkedWord":"","Notes":"","Spanish":"PLAYA","Italian":"SPIAGGIA"},{"Id":"bear","Active":"1","Text":"BEAR","DrawingId":"bear","Value":"","SortValue":"","Drawing":"49","Kind":"Noun","Category":"Animals","PlaySessionLink":"","Tags":"","Complexity":"4","Gender":"","Form":"Singular","Article":"","LinkedWord":"","Notes":"","Spanish":"OSO","Italian":"ORSO"},{"Id":"bed","Active":"1","Text":"BED","DrawingId":"bed","Value":"","SortValue":"","Drawing":"4A","Kind":"Noun","Category":"Home","PlaySessionLink":"","Tags":"","Complexity":"3","Gender":"","Form":"","Article":"","LinkedWord":"","Notes":"","Spanish":"CAMA","Italian":"LETTO"},{"Id":"bedroom","Active":"1","Text":"BEDROOM","DrawingId":"bedroom","Value":"","SortValue":"","Drawing":"3A","Kind":"Noun","Category":"Home","PlaySessionLink":"","Tags":"","Complexity":"7","Gender":"","Form":"","Article":"","LinkedWord":"","Notes":"","Spanish":"DORMITORIO","Italian":"CAMERA DA LETTO"},{"Id":"bee","Active":"1","Text":"BEE","DrawingId":"bee","Value":"","SortValue":"","Drawing":"174","Kind":"Noun","Category":"Animals","PlaySessionLink":"","Tags":"","Complexity":"3","Gender":"","Form":"","Article":"","LinkedWord":"","Notes":"","Spanish":"ABEJA","Italian":"APE"},{"Id":"belly","Active":"1","Text":"BELLY","DrawingId":"belly","Value":"","SortValue":"","Drawing":"4B","Kind":"Noun","Category":"Body","PlaySessionLink":"","Tags":"","Complexity":"5","Gender":"","Form":"","Article":"","LinkedWord":"","Notes":"","Spanish":"BARRIGA","Italian":"PANCIA"},{"Id":"bicycle","Active":"1","Text":"BICYCLE","DrawingId":"bicycle","Value":"","SortValue":"","Drawing":"1E84","Kind":"Noun","Category":"City","PlaySessionLink":"","Tags":"","Complexity":"7","Gender":"","Form":"","Article":"","LinkedWord":"","Notes":"","Spanish":"BICICLETA","Italian":"BICICLETTA"},{"Id":"bird","Active":"1","Text":"BIRD","DrawingId":"bird","Value":"","SortValue":"","Drawing":"4D","Kind":"Noun","Category":"Animals","PlaySessionLink":"","Tags":"","Complexity":"4","Gender":"","Form":"Singular","Article":"","LinkedWord":"","Notes":"","Spanish":"PÁJARO","Italian":"UCCELLO"},{"Id":"book","Active":"1","Text":"BOOK","DrawingId":"book","Value":"","SortValue":"","Drawing":"4E","Kind":"Noun","Category":"Objects","PlaySessionLink":"","Tags":"","Complexity":"4","Gender":"","Form":"Singular","Article":"","LinkedWord":"","Notes":"","Spanish":"LIBRO","Italian":"LIBRO"},{"Id":"box","Active":"1","Text":"BOX","DrawingId":"box","Value":"","SortValue":"","Drawing":"50","Kind":"Noun","Category":"Objects","PlaySessionLink":"","Tags":"","Complexity":"3","Gender":"","Form":"","Article":"","LinkedWord":"","Notes":"","Spanish":"CAJA","Italian":"SCATOLA"},{"Id":"boy","Active":"1","Text":"BOY","DrawingId":"boy","Value":"","SortValue":"","Drawing":"51","Kind":"Noun","Category":"Family","PlaySessionLink":"","Tags":"","Complexity":"3","Gender":"","Form":"","Article":"","LinkedWord":"","Notes":"","Spanish":"NIÑO","Italian":"RAGAZZO"},{"Id":"brain","Active":"1","Text":"BRAIN","DrawingId":"brain","Value":"","SortValue":"","Drawing":"52","Kind":"Noun","Category":"Body","PlaySessionLink":"","Tags":"","Complexity":"5","Gender":"","Form":"","Article":"","LinkedWord":"","Notes":"","Spanish":"CEREBRO","Italian":"CERVELLO"},{"Id":"bread","Active":"1","Text":"BREAD","DrawingId":"bread","Value":"","SortValue":"","Drawing":"53","Kind":"Noun","Category":"Food","PlaySessionLink":"","Tags":"","Complexity":"5","Gender":"","Form":"","Article":"","LinkedWord":"","Notes":"","Spanish":"PAN","Italian":"PANE"},{"Id":"breast","Active":"0","Text":"BREAST","DrawingId":"","Value":"","SortValue":"","Drawing":"","Kind":"Noun","Category":"Body","PlaySessionLink":"","Tags":"","Complexity":"","Gender":"","Form":"","Article":"","LinkedWord":"","Notes":"","Spanish":"PECHO","Italian":""},{"Id":"breeze","Active":"1","Text":"BREEZE","DrawingId":"breeze","Value":"","SortValue":"","Drawing":"54","Kind":"Noun","Category":"Nature","PlaySessionLink":"","Tags":"","Complexity":"6","Gender":"","Form":"","Article":"","LinkedWord":"","Notes":"","Spanish":"BRISA","Italian":"BREZZA"},{"Id":"brother","Active":"1","Text":"BROTHER","DrawingId":"brother","Value":"","SortValue":"","Drawing":"2F","Kind":"Noun","Category":"Family","PlaySessionLink":"","Tags":"","Complexity":"7","Gender":"","Form":"","Article":"","LinkedWord":"","Notes":"","Spanish":"HERMANO","Italian":"FRATELLO"},{"Id":"bus","Active":"1","Text":"BUS","DrawingId":"bus","Value":"","SortValue":"","Drawing":"44","Kind":"Noun","Category":"City","PlaySessionLink":"","Tags":"","Complexity":"3","Gender":"","Form":"","Article":"","LinkedWord":"","Notes":"","Spanish":"OMNIBUS","Italian":"AUTOBUS"},{"Id":"cake","Active":"1","Text":"CAKE","DrawingId":"cake","Value":"","SortValue":"","Drawing":"1E85","Kind":"Noun","Category":"Food","PlaySessionLink":"","Tags":"","Complexity":"4","Gender":"","Form":"","Article":"","LinkedWord":"","Notes":"","Spanish":"TORTA","Italian":"TORTA"},{"Id":"camel","Active":"1","Text":"CAMEL","DrawingId":"camel","Value":"","SortValue":"","Drawing":"56","Kind":"Noun","Category":"Animals","PlaySessionLink":"","Tags":"","Complexity":"5","Gender":"","Form":"","Article":"","LinkedWord":"","Notes":"","Spanish":"CAMELLO","Italian":"CAMMELLO"},{"Id":"car","Active":"1","Text":"CAR","DrawingId":"car","Value":"","SortValue":"","Drawing":"2044","Kind":"Noun","Category":"City","PlaySessionLink":"","Tags":"","Complexity":"3","Gender":"","Form":"","Article":"","LinkedWord":"","Notes":"","Spanish":"AUTO","Italian":"MACCHINA"},{"Id":"carrot","Active":"1","Text":"CARROT","DrawingId":"carrot","Value":"","SortValue":"","Drawing":"58","Kind":"Noun","Category":"Food","PlaySessionLink":"","Tags":"","Complexity":"6","Gender":"","Form":"","Article":"","LinkedWord":"","Notes":"","Spanish":"ZANAHORIA","Italian":"CAROTA"},{"Id":"castle","Active":"1","Text":"CASTLE","DrawingId":"castle","Value":"","SortValue":"","Drawing":"1E80","Kind":"Noun","Category":"City","PlaySessionLink":"","Tags":"","Complexity":"6","Gender":"","Form":"","Article":"","LinkedWord":"","Notes":"","Spanish":"CASTILLO","Italian":"CASTELLO"},{"Id":"cat","Active":"1","Text":"CAT","DrawingId":"cat","Value":"","SortValue":"","Drawing":"59","Kind":"Noun","Category":"Animals","PlaySessionLink":"","Tags":"","Complexity":"3","Gender":"","Form":"Singular","Article":"","LinkedWord":"","Notes":"","Spanish":"GATO","Italian":"GATTO"},{"Id":"chair","Active":"1","Text":"CHAIR","DrawingId":"chair","Value":"","SortValue":"","Drawing":"5A","Kind":"Noun","Category":"Home","PlaySessionLink":"","Tags":"","Complexity":"5","Gender":"","Form":"","Article":"","LinkedWord":"","Notes":"","Spanish":"SILLA","Italian":"SEDIA"},{"Id":"cheese","Active":"1","Text":"CHEESE","DrawingId":"cheese","Value":"","SortValue":"","Drawing":"61","Kind":"Noun","Category":"Food","PlaySessionLink":"","Tags":"","Complexity":"6","Gender":"","Form":"","Article":"","LinkedWord":"","Notes":"","Spanish":"QUESO","Italian":"FORMAGGIO"},{"Id":"cherry","Active":"1","Text":"CHERRY","DrawingId":"cherry","Value":"","SortValue":"","Drawing":"62","Kind":"Noun","Category":"Food","PlaySessionLink":"","Tags":"","Complexity":"6","Gender":"","Form":"","Article":"","LinkedWord":"","Notes":"","Spanish":"CEREZA","Italian":"CILIEGIA"},{"Id":"chest","Active":"1","Text":"CHEST","DrawingId":"chest","Value":"","SortValue":"","Drawing":"63","Kind":"Noun","Category":"Body","PlaySessionLink":"","Tags":"","Complexity":"5","Gender":"","Form":"","Article":"","LinkedWord":"","Notes":"","Spanish":"PECHO","Italian":"PETTO"},{"Id":"chicken","Active":"1","Text":"CHICKEN","DrawingId":"chicken","Value":"","SortValue":"","Drawing":"1E81","Kind":"Noun","Category":"Animals","PlaySessionLink":"","Tags":"","Complexity":"7","Gender":"","Form":"","Article":"","LinkedWord":"","Notes":"","Spanish":"POLLO","Italian":"POLLO"},{"Id":"chickpea","Active":"1","Text":"CHICKPEA","DrawingId":"chickpea","Value":"","SortValue":"","Drawing":"64","Kind":"Noun","Category":"Food","PlaySessionLink":"","Tags":"","Complexity":"8","Gender":"","Form":"","Article":"","LinkedWord":"","Notes":"","Spanish":"GARBANZO","Italian":"CECE"},{"Id":"church","Active":"1","Text":"CHURCH","DrawingId":"church","Value":"","SortValue":"","Drawing":"0176","Kind":"Noun","Category":"City","PlaySessionLink":"","Tags":"","Complexity":"6","Gender":"","Form":"","Article":"","LinkedWord":"","Notes":"","Spanish":"IGLESIA","Italian":"CHIESA"},{"Id":"city","Active":"1","Text":"CITY","DrawingId":"city","Value":"","SortValue":"","Drawing":"178","Kind":"Noun","Category":"City","PlaySessionLink":"","Tags":"","Complexity":"4","Gender":"","Form":"","Article":"","LinkedWord":"","Notes":"","Spanish":"CIUDAD","Italian":"CITTÀ"},{"Id":"classroom","Active":"1","Text":"CLASSROOM","DrawingId":"classroom","Value":"","SortValue":"","Drawing":"30","Kind":"Noun","Category":"City","PlaySessionLink":"","Tags":"","Complexity":"9","Gender":"","Form":"","Article":"","LinkedWord":"","Notes":"","Spanish":"AULA","Italian":"AULA"},{"Id":"closet","Active":"1","Text":"CLOSET","DrawingId":"closet","Value":"","SortValue":"","Drawing":"1EF2","Kind":"Noun","Category":"Home","PlaySessionLink":"","Tags":"","Complexity":"6","Gender":"","Form":"","Article":"","LinkedWord":"","Notes":"","Spanish":"PLACARD","Italian":"ARMADIO"},{"Id":"cloud","Active":"1","Text":"CLOUD","DrawingId":"cloud","Value":"","SortValue":"","Drawing":"65","Kind":"Noun","Category":"Nature","PlaySessionLink":"","Tags":"","Complexity":"5","Gender":"","Form":"","Article":"","LinkedWord":"","Notes":"","Spanish":"NUBE","Italian":"NUVOLA"},{"Id":"coat","Active":"1","Text":"COAT","DrawingId":"coat","Value":"","SortValue":"","Drawing":"104","Kind":"Noun","Category":"Clothes","PlaySessionLink":"","Tags":"","Complexity":"4","Gender":"","Form":"","Article":"","LinkedWord":"","Notes":"","Spanish":"ABRIGO","Italian":"CAPPOTTO"},{"Id":"coffee","Active":"1","Text":"COFFEE","DrawingId":"coffee","Value":"","SortValue":"","Drawing":"10D","Kind":"Noun","Category":"Food","PlaySessionLink":"","Tags":"","Complexity":"6","Gender":"","Form":"","Article":"","LinkedWord":"","Notes":"","Spanish":"CAFÉ","Italian":"CAFFÈ"},{"Id":"color_black","Active":"1","Text":"BLACK","DrawingId":"color_black","Value":"black","SortValue":"11","Drawing":"100","Kind":"Adjective","Category":"Colors","PlaySessionLink":"","Tags":"","Complexity":"5","Gender":"","Form":"Singular","Article":"","LinkedWord":"","Notes":"","Spanish":"NEGRO","Italian":"NERO"},{"Id":"color_blue","Active":"1","Text":"BLUE","DrawingId":"color_blue","Value":"blue","SortValue":"6","Drawing":"100","Kind":"Adjective","Category":"Colors","PlaySessionLink":"","Tags":"","Complexity":"4","Gender":"","Form":"Singular","Article":"","LinkedWord":"","Notes":"","Spanish":"AZUL","Italian":"BLU"},{"Id":"color_brown","Active":"1","Text":"BROWN","DrawingId":"color_brown","Value":"brown","SortValue":"1","Drawing":"100","Kind":"Adjective","Category":"Colors","PlaySessionLink":"","Tags":"","Complexity":"5","Gender":"","Form":"Singular","Article":"","LinkedWord":"","Notes":"","Spanish":"MARRÓN","Italian":"MARRONE"},{"Id":"color_gold","Active":"0","Text":"GOLD","DrawingId":"color_gold","Value":"gold","SortValue":"","Drawing":"100","Kind":"Adjective","Category":"Colors","PlaySessionLink":"","Tags":"","Complexity":"","Gender":"","Form":"Singular","Article":"","LinkedWord":"","Notes":"","Spanish":"ORO","Italian":""},{"Id":"color_green","Active":"1","Text":"GREEN","DrawingId":"color_green","Value":"green","SortValue":"5","Drawing":"100","Kind":"Adjective","Category":"Colors","PlaySessionLink":"","Tags":"","Complexity":"5","Gender":"","Form":"Singular","Article":"","LinkedWord":"","Notes":"","Spanish":"VERDE","Italian":"VERDE"},{"Id":"color_grey","Active":"1","Text":"GREY","DrawingId":"color_grey","Value":"grey","SortValue":"10","Drawing":"100","Kind":"Adjective","Category":"Colors","PlaySessionLink":"","Tags":"","Complexity":"4","Gender":"","Form":"Singular","Article":"","LinkedWord":"","Notes":"newly added (need to define color?)","Spanish":"GRIS","Italian":"GRIGIO"},{"Id":"color_orange","Active":"1","Text":"ORANGE","DrawingId":"color_orange","Value":"orange","SortValue":"3","Drawing":"100","Kind":"Adjective","Category":"Colors","PlaySessionLink":"","Tags":"","Complexity":"6","Gender":"","Form":"Singular","Article":"","LinkedWord":"","Notes":"","Spanish":"NARANJA","Italian":"ARANCIONE"},{"Id":"color_pink","Active":"1","Text":"PINK","DrawingId":"color_pink","Value":"pink","SortValue":"8","Drawing":"100","Kind":"Adjective","Category":"Colors","PlaySessionLink":"","Tags":"","Complexity":"4","Gender":"","Form":"Singular","Article":"","LinkedWord":"","Notes":"","Spanish":"ROSADO","Italian":"ROSA"},{"Id":"color_purple","Active":"1","Text":"PURPLE","DrawingId":"color_purple","Value":"purple","SortValue":"7","Drawing":"100","Kind":"Adjective","Category":"Colors","PlaySessionLink":"","Tags":"","Complexity":"6","Gender":"","Form":"Singular","Article":"","LinkedWord":"","Notes":"newly added (need to define color?)","Spanish":"MORADO","Italian":"VIOLA"},{"Id":"color_red","Active":"1","Text":"RED","DrawingId":"color_red","Value":"red","SortValue":"2","Drawing":"100","Kind":"Adjective","Category":"Colors","PlaySessionLink":"","Tags":"","Complexity":"3","Gender":"","Form":"Singular","Article":"","LinkedWord":"","Notes":"","Spanish":"ROJO","Italian":"ROSSO"},{"Id":"color_silver","Active":"0","Text":"SILVER","DrawingId":"color_silver","Value":"silver","SortValue":"","Drawing":"100","Kind":"Adjective","Category":"Colors","PlaySessionLink":"","Tags":"","Complexity":"","Gender":"","Form":"Singular","Article":"","LinkedWord":"","Notes":"","Spanish":"PLATA","Italian":""},{"Id":"color_white","Active":"1","Text":"WHITE","DrawingId":"color_white","Value":"","SortValue":"9","Drawing":"1EA7","Kind":"Adjective","Category":"Colors","PlaySessionLink":"","Tags":"","Complexity":"5","Gender":"","Form":"Singular","Article":"","LinkedWord":"","Notes":"","Spanish":"BLANCO","Italian":"BIANCO"},{"Id":"color_yellow","Active":"1","Text":"YELLOW","DrawingId":"color_yellow","Value":"yellow","SortValue":"4","Drawing":"100","Kind":"Adjective","Category":"Colors","PlaySessionLink":"","Tags":"","Complexity":"6","Gender":"","Form":"Singular","Article":"","LinkedWord":"","Notes":"","Spanish":"AMARILLO","Italian":"GIALLO"},{"Id":"computer","Active":"1","Text":"COMPUTER","DrawingId":"computer","Value":"","SortValue":"","Drawing":"1EF3","Kind":"Noun","Category":"Home","PlaySessionLink":"","Tags":"","Complexity":"8","Gender":"","Form":"","Article":"","LinkedWord":"","Notes":"","Spanish":"COMPUTADORA","Italian":"COMPUTER"},{"Id":"couch","Active":"1","Text":"COUCH","DrawingId":"couch","Value":"","SortValue":"","Drawing":"155","Kind":"Noun","Category":"Home","PlaySessionLink":"","Tags":"","Complexity":"5","Gender":"","Form":"","Article":"","LinkedWord":"","Notes":"","Spanish":"SOFÁ","Italian":"DIVANO"},{"Id":"cow","Active":"1","Text":"COW","DrawingId":"cow","Value":"","SortValue":"","Drawing":"158","Kind":"Noun","Category":"Animals","PlaySessionLink":"","Tags":"","Complexity":"3","Gender":"","Form":"","Article":"","LinkedWord":"","Notes":"","Spanish":"VACA","Italian":"MUCCA"},{"Id":"crocodile","Active":"1","Text":"CROCODILE","DrawingId":"crocodile","Value":"","SortValue":"","Drawing":"159","Kind":"Noun","Category":"Animals","PlaySessionLink":"","Tags":"","Complexity":"9","Gender":"","Form":"","Article":"","LinkedWord":"","Notes":"","Spanish":"COCODRILO","Italian":"COCCODRILLO"},{"Id":"cucumber","Active":"1","Text":"CUCUMBER","DrawingId":"cucumber","Value":"","SortValue":"","Drawing":"68","Kind":"Noun","Category":"Food","PlaySessionLink":"","Tags":"","Complexity":"8","Gender":"","Form":"","Article":"","LinkedWord":"","Notes":"","Spanish":"PEPINO","Italian":"CETRIOLO"},{"Id":"cup","Active":"1","Text":"CUP","DrawingId":"cup","Value":"","SortValue":"","Drawing":"156","Kind":"Noun","Category":"Home","PlaySessionLink":"","Tags":"","Complexity":"3","Gender":"","Form":"","Article":"","LinkedWord":"","Notes":"","Spanish":"TAZA","Italian":"TAZZA"},{"Id":"daughter","Active":"1","Text":"DAUGHTER","DrawingId":"daughter","Value":"","SortValue":"","Drawing":"157","Kind":"Noun","Category":"Family","PlaySessionLink":"","Tags":"","Complexity":"8","Gender":"","Form":"","Article":"","LinkedWord":"","Notes":"","Spanish":"HIJA","Italian":"FIGLIA"},{"Id":"day_friday","Active":"1","Text":"FRIDAY","DrawingId":"day_friday","Value":"5","SortValue":"5","Drawing":"2212","Kind":"Noun","Category":"Days","PlaySessionLink":"","Tags":"","Complexity":"6","Gender":"","Form":"","Article":"","LinkedWord":"","Notes":"","Spanish":"VIERNES","Italian":"VENERDÌ"},{"Id":"day_monday","Active":"1","Text":"MONDAY","DrawingId":"day_monday","Value":"1","SortValue":"1","Drawing":"D7","Kind":"Noun","Category":"Days","PlaySessionLink":"","Tags":"","Complexity":"6","Gender":"","Form":"","Article":"","LinkedWord":"","Notes":"","Spanish":"LUNES","Italian":"LUNEDÌ"},{"Id":"day_saturday","Active":"1","Text":"SATURDAY","DrawingId":"day_saturday","Value":"6","SortValue":"6","Drawing":"F7","Kind":"Noun","Category":"Days","PlaySessionLink":"","Tags":"","Complexity":"8","Gender":"","Form":"","Article":"","LinkedWord":"","Notes":"","Spanish":"SÁBADO","Italian":"SABATO"},{"Id":"day_sunday","Active":"1","Text":"SUNDAY","DrawingId":"day_sunday","Value":"7","SortValue":"7","Drawing":"3D","Kind":"Noun","Category":"Days","PlaySessionLink":"","Tags":"","Complexity":"6","Gender":"","Form":"","Article":"","LinkedWord":"","Notes":"","Spanish":"DOMINGO","Italian":"DOMENICA"},{"Id":"day_thursday","Active":"1","Text":"THURSDAY","DrawingId":"day_thursday","Value":"4","SortValue":"4","Drawing":"2260","Kind":"Noun","Category":"Days","PlaySessionLink":"","Tags":"","Complexity":"8","Gender":"","Form":"","Article":"","LinkedWord":"","Notes":"","Spanish":"JUEVES","Italian":"GIOVEDÌ"},{"Id":"day_tuesday","Active":"1","Text":"TUESDAY","DrawingId":"day_tuesday","Value":"2","SortValue":"2","Drawing":"3E","Kind":"Noun","Category":"Days","PlaySessionLink":"","Tags":"","Complexity":"7","Gender":"","Form":"","Article":"","LinkedWord":"","Notes":"","Spanish":"MARTES","Italian":"MARTEDÌ"},{"Id":"day_wednesday","Active":"1","Text":"WEDNESDAY","DrawingId":"day_wednesday","Value":"3","SortValue":"3","Drawing":"3C","Kind":"Noun","Category":"Days","PlaySessionLink":"","Tags":"","Complexity":"9","Gender":"","Form":"","Article":"","LinkedWord":"","Notes":"","Spanish":"MIÉRCOLES","Italian":"MERCOLEDÌ"},{"Id":"desert","Active":"1","Text":"DESERT","DrawingId":"desert","Value":"","SortValue":"","Drawing":"015A","Kind":"Noun","Category":"Nature","PlaySessionLink":"","Tags":"","Complexity":"6","Gender":"","Form":"","Article":"","LinkedWord":"","Notes":"","Spanish":"DESIERTO","Italian":"DESERTO"},{"Id":"dish","Active":"1","Text":"DISH","DrawingId":"dish","Value":"","SortValue":"","Drawing":"151","Kind":"Noun","Category":"Home","PlaySessionLink":"","Tags":"","Complexity":"4","Gender":"","Form":"","Article":"","LinkedWord":"","Notes":"","Spanish":"PLATO","Italian":"PIATTO"},{"Id":"dog","Active":"1","Text":"DOG","DrawingId":"dog","Value":"","SortValue":"","Drawing":"6B","Kind":"Noun","Category":"Animals","PlaySessionLink":"","Tags":"","Complexity":"3","Gender":"","Form":"Singular","Article":"","LinkedWord":"","Notes":"","Spanish":"PERRO","Italian":"CANE"},{"Id":"doll","Active":"1","Text":"DOLL","DrawingId":"doll","Value":"","SortValue":"","Drawing":"014D","Kind":"Noun","Category":"Objects","PlaySessionLink":"","Tags":"","Complexity":"4","Gender":"","Form":"","Article":"","LinkedWord":"","Notes":"","Spanish":"MUÑECA","Italian":"BAMBOLA"},{"Id":"door","Active":"1","Text":"DOOR","DrawingId":"door","Value":"","SortValue":"","Drawing":"6C","Kind":"Noun","Category":"Home","PlaySessionLink":"","Tags":"","Complexity":"4","Gender":"","Form":"","Article":"","LinkedWord":"","Notes":"","Spanish":"PUERTA","Italian":"PORTA"},{"Id":"duck","Active":"1","Text":"DUCK","DrawingId":"duck","Value":"","SortValue":"","Drawing":"31","Kind":"Noun","Category":"Animals","PlaySessionLink":"","Tags":"","Complexity":"4","Gender":"","Form":"","Article":"","LinkedWord":"","Notes":"","Spanish":"PATO","Italian":"ANATRA"},{"Id":"ear","Active":"1","Text":"EAR","DrawingId":"ear","Value":"","SortValue":"","Drawing":"6E","Kind":"Noun","Category":"Body","PlaySessionLink":"","Tags":"","Complexity":"3","Gender":"","Form":"","Article":"","LinkedWord":"","Notes":"","Spanish":"OREJA","Italian":"ORECCHIO"},{"Id":"elephant","Active":"1","Text":"ELEPHANT","DrawingId":"elephant","Value":"","SortValue":"","Drawing":"6F","Kind":"Noun","Category":"Animals","PlaySessionLink":"","Tags":"","Complexity":"8","Gender":"","Form":"Singular","Article":"","LinkedWord":"","Notes":"","Spanish":"ELEFANTE","Italian":"ELEFANTE"},{"Id":"eye","Active":"1","Text":"EYE","DrawingId":"eye","Value":"","SortValue":"","Drawing":"70","Kind":"Noun","Category":"Body","PlaySessionLink":"","Tags":"","Complexity":"3","Gender":"","Form":"","Article":"","LinkedWord":"","Notes":"","Spanish":"OJO","Italian":"OCCHIO"},{"Id":"face","Active":"1","Text":"FACE","DrawingId":"face","Value":"","SortValue":"","Drawing":"71","Kind":"Noun","Category":"Body","PlaySessionLink":"","Tags":"","Complexity":"4","Gender":"","Form":"","Article":"","LinkedWord":"","Notes":"","Spanish":"CARA","Italian":"VISO"},{"Id":"father","Active":"1","Text":"FATHER","DrawingId":"father","Value":"","SortValue":"","Drawing":"5B","Kind":"Noun","Category":"Family","PlaySessionLink":"","Tags":"","Complexity":"6","Gender":"","Form":"","Article":"","LinkedWord":"","Notes":"","Spanish":"PADRE","Italian":"PADRE"},{"Id":"field","Active":"1","Text":"FIELD","DrawingId":"field","Value":"","SortValue":"","Drawing":"73","Kind":"Noun","Category":"City","PlaySessionLink":"","Tags":"","Complexity":"5","Gender":"","Form":"","Article":"","LinkedWord":"","Notes":"","Spanish":"CAMPO","Italian":"CAMPO"},{"Id":"finger","Active":"1","Text":"FINGER","DrawingId":"finger","Value":"","SortValue":"","Drawing":"75","Kind":"Noun","Category":"Body","PlaySessionLink":"","Tags":"","Complexity":"6","Gender":"","Form":"","Article":"","LinkedWord":"","Notes":"","Spanish":"DEDO","Italian":"DITO"},{"Id":"fire","Active":"1","Text":"FIRE","DrawingId":"fire","Value":"","SortValue":"","Drawing":"139","Kind":"Noun","Category":"Nature","PlaySessionLink":"","Tags":"","Complexity":"4","Gender":"","Form":"","Article":"","LinkedWord":"","Notes":"","Spanish":"FUEGO","Italian":"FUOCO"},{"Id":"floor","Active":"1","Text":"FLOOR","DrawingId":"floor","Value":"","SortValue":"","Drawing":"146","Kind":"Noun","Category":"Home","PlaySessionLink":"","Tags":"","Complexity":"5","Gender":"","Form":"","Article":"","LinkedWord":"","Notes":"","Spanish":"SUELO","Italian":"PAVIMENTO"},{"Id":"flower","Active":"1","Text":"FLOWER","DrawingId":"flower","Value":"","SortValue":"","Drawing":"77","Kind":"Noun","Category":"Nature","PlaySessionLink":"","Tags":"","Complexity":"6","Gender":"","Form":"Singular","Article":"","LinkedWord":"","Notes":"","Spanish":"FLOR","Italian":"FIORE"},{"Id":"food","Active":"1","Text":"FOOD","DrawingId":"food","Value":"","SortValue":"","Drawing":"5D","Kind":"Noun","Category":"Food","PlaySessionLink":"","Tags":"","Complexity":"4","Gender":"","Form":"","Article":"","LinkedWord":"","Notes":"","Spanish":"COMIDA","Italian":"CIBO"},{"Id":"foot","Active":"1","Text":"FOOT","DrawingId":"foot","Value":"","SortValue":"","Drawing":"CC","Kind":"Noun","Category":"Body","PlaySessionLink":"","Tags":"","Complexity":"4","Gender":"","Form":"","Article":"","LinkedWord":"","Notes":"","Spanish":"PIE","Italian":"PIEDE"},{"Id":"forest","Active":"1","Text":"FOREST","DrawingId":"forest","Value":"","SortValue":"","Drawing":"79","Kind":"Noun","Category":"Nature","PlaySessionLink":"","Tags":"","Complexity":"6","Gender":"","Form":"","Article":"","LinkedWord":"","Notes":"","Spanish":"BOSQUE","Italian":"FORESTA"},{"Id":"fork","Active":"1","Text":"FORK","DrawingId":"fork","Value":"","SortValue":"","Drawing":"015B","Kind":"Noun","Category":"Home","PlaySessionLink":"","Tags":"","Complexity":"4","Gender":"","Form":"","Article":"","LinkedWord":"","Notes":"","Spanish":"TENEDOR","Italian":"FORCHETTA"},{"Id":"fox","Active":"1","Text":"FOX","DrawingId":"fox","Value":"","SortValue":"","Drawing":"13D","Kind":"Noun","Category":"Animals","PlaySessionLink":"","Tags":"","Complexity":"3","Gender":"","Form":"","Article":"","LinkedWord":"","Notes":"","Spanish":"ZORRO","Italian":"VOLPE"},{"Id":"fridge","Active":"1","Text":"FRIDGE","DrawingId":"fridge","Value":"","SortValue":"","Drawing":"7A","Kind":"Noun","Category":"Home","PlaySessionLink":"","Tags":"","Complexity":"6","Gender":"","Form":"","Article":"","LinkedWord":"","Notes":"","Spanish":"HELADERA","Italian":"FRIGORIFERO"},{"Id":"frog","Active":"1","Text":"FROG","DrawingId":"frog","Value":"","SortValue":"","Drawing":"13B","Kind":"Noun","Category":"Animals","PlaySessionLink":"","Tags":"","Complexity":"4","Gender":"","Form":"","Article":"","LinkedWord":"","Notes":"","Spanish":"RANA","Italian":"RANA"},{"Id":"garden","Active":"1","Text":"GARDEN","DrawingId":"garden","Value":"","SortValue":"","Drawing":"C2","Kind":"Noun","Category":"City","PlaySessionLink":"","Tags":"","Complexity":"6","Gender":"","Form":"","Article":"","LinkedWord":"","Notes":"","Spanish":"JARDÍN","Italian":"GIARDINO"},{"Id":"garlic","Active":"1","Text":"GARLIC","DrawingId":"garlic","Value":"","SortValue":"","Drawing":"C4","Kind":"Noun","Category":"Food","PlaySessionLink":"","Tags":"","Complexity":"6","Gender":"","Form":"","Article":"","LinkedWord":"","Notes":"","Spanish":"AJO","Italian":"AGLIO"},{"Id":"girl","Active":"1","Text":"GIRL","DrawingId":"girl","Value":"","SortValue":"","Drawing":"C0","Kind":"Noun","Category":"Family","PlaySessionLink":"","Tags":"","Complexity":"4","Gender":"","Form":"","Article":"","LinkedWord":"","Notes":"","Spanish":"NIÑA","Italian":"RAGAZZA"},{"Id":"gloves","Active":"1","Text":"GLOVES","DrawingId":"gloves","Value":"","SortValue":"","Drawing":"141","Kind":"Noun","Category":"Clothes","PlaySessionLink":"","Tags":"","Complexity":"6","Gender":"","Form":"","Article":"","LinkedWord":"","Notes":"","Spanish":"GUANTES","Italian":"GUANTI"},{"Id":"glue","Active":"1","Text":"GLUE","DrawingId":"glue","Value":"","SortValue":"","Drawing":"C5","Kind":"Noun","Category":"Objects","PlaySessionLink":"","Tags":"","Complexity":"4","Gender":"","Form":"","Article":"","LinkedWord":"","Notes":"","Spanish":"COLA","Italian":"COLLA"},{"Id":"goat","Active":"1","Text":"GOAT","DrawingId":"goat","Value":"","SortValue":"","Drawing":"160","Kind":"Noun","Category":"Animals","PlaySessionLink":"","Tags":"","Complexity":"4","Gender":"","Form":"","Article":"","LinkedWord":"","Notes":"","Spanish":"CABRA","Italian":"CAPRA"},{"Id":"grandaughter","Active":"1","Text":"GRANDDAUGHTER","DrawingId":"grandaughter","Value":"","SortValue":"","Drawing":"33","Kind":"Noun","Category":"Family","PlaySessionLink":"","Tags":"","Complexity":"13","Gender":"","Form":"","Article":"","LinkedWord":"","Notes":"","Spanish":"NIETA","Italian":"NIPOTINA"},{"Id":"grandfather","Active":"1","Text":"GRANDFATHER","DrawingId":"grandfather","Value":"","SortValue":"","Drawing":"34","Kind":"Noun","Category":"Family","PlaySessionLink":"","Tags":"","Complexity":"11","Gender":"","Form":"","Article":"","LinkedWord":"","Notes":"","Spanish":"ABUELO","Italian":"NONNO"},{"Id":"grandmother","Active":"1","Text":"GRANDMOTHER","DrawingId":"grandmother","Value":"","SortValue":"","Drawing":"35","Kind":"Noun","Category":"Family","PlaySessionLink":"","Tags":"","Complexity":"11","Gender":"","Form":"","Article":"","LinkedWord":"","Notes":"","Spanish":"ABUELA","Italian":"NONNA"},{"Id":"grandson","Active":"1","Text":"GRANDSON","DrawingId":"grandson","Value":"","SortValue":"","Drawing":"36","Kind":"Noun","Category":"Family","PlaySessionLink":"","Tags":"","Complexity":"8","Gender":"","Form":"","Article":"","LinkedWord":"","Notes":"","Spanish":"NIETO","Italian":"NIPOTE"},{"Id":"grapes","Active":"1","Text":"GRAPES","DrawingId":"grapes","Value":"","SortValue":"","Drawing":"C6","Kind":"Noun","Category":"Food","PlaySessionLink":"","Tags":"","Complexity":"6","Gender":"","Form":"","Article":"","LinkedWord":"","Notes":"","Spanish":"UVAS","Italian":"UVA"},{"Id":"hair","Active":"1","Text":"HAIR","DrawingId":"hair","Value":"","SortValue":"","Drawing":"C7","Kind":"Noun","Category":"Body","PlaySessionLink":"","Tags":"","Complexity":"4","Gender":"","Form":"","Article":"","LinkedWord":"","Notes":"","Spanish":"PELO","Italian":"CAPELLI"},{"Id":"hand","Active":"1","Text":"HAND","DrawingId":"hand","Value":"","SortValue":"","Drawing":"D0","Kind":"Noun","Category":"Body","PlaySessionLink":"","Tags":"","Complexity":"4","Gender":"","Form":"","Article":"","LinkedWord":"","Notes":"","Spanish":"MANO","Italian":"MANO"},{"Id":"hat","Active":"1","Text":"HAT","DrawingId":"hat","Value":"","SortValue":"","Drawing":"C9","Kind":"Noun","Category":"Clothes","PlaySessionLink":"","Tags":"","Complexity":"3","Gender":"","Form":"","Article":"","LinkedWord":"","Notes":"","Spanish":"SOMBRERO","Italian":"CAPPELLO"},{"Id":"head","Active":"1","Text":"HEAD","DrawingId":"head","Value":"","SortValue":"","Drawing":"CA","Kind":"Noun","Category":"Body","PlaySessionLink":"","Tags":"","Complexity":"4","Gender":"","Form":"","Article":"","LinkedWord":"","Notes":"","Spanish":"CABEZA","Italian":"TESTA"},{"Id":"hill","Active":"1","Text":"HILL","DrawingId":"hill","Value":"","SortValue":"","Drawing":"143","Kind":"Noun","Category":"Nature","PlaySessionLink":"","Tags":"","Complexity":"4","Gender":"","Form":"","Article":"","LinkedWord":"","Notes":"","Spanish":"COLINA","Italian":"COLLINA"},{"Id":"horse","Active":"1","Text":"HORSE","DrawingId":"horse","Value":"","SortValue":"","Drawing":"161","Kind":"Noun","Category":"Animals","PlaySessionLink":"","Tags":"","Complexity":"5","Gender":"","Form":"","Article":"","LinkedWord":"","Notes":"","Spanish":"CABALLO","Italian":"CAVALLO"},{"Id":"hospital","Active":"1","Text":"HOSPITAL","DrawingId":"hospital","Value":"","SortValue":"","Drawing":"CB","Kind":"Noun","Category":"City","PlaySessionLink":"","Tags":"","Complexity":"8","Gender":"","Form":"","Article":"","LinkedWord":"","Notes":"","Spanish":"HOSPITAL","Italian":"OSPEDALE"},{"Id":"house","Active":"1","Text":"HOUSE","DrawingId":"house","Value":"","SortValue":"","Drawing":"C8","Kind":"Noun","Category":"City","PlaySessionLink":"","Tags":"","Complexity":"5","Gender":"","Form":"","Article":"","LinkedWord":"","Notes":"","Spanish":"CASA","Italian":"CASA"},{"Id":"ice-cream","Active":"0","Text":"ICE-CREAM","DrawingId":"cd","Value":"","SortValue":"","Drawing":"CD","Kind":"Noun","Category":"Food","PlaySessionLink":"","Tags":"","Complexity":"","Gender":"","Form":"","Article":"","LinkedWord":"","Notes":"","Spanish":"HELADO","Italian":""},{"Id":"island","Active":"1","Text":"ISLAND","DrawingId":"island","Value":"","SortValue":"","Drawing":"CE","Kind":"Noun","Category":"Nature","PlaySessionLink":"","Tags":"","Complexity":"6","Gender":"","Form":"","Article":"","LinkedWord":"","Notes":"","Spanish":"ISLA","Italian":"ISOLA"},{"Id":"jacket","Active":"1","Text":"JACKET","DrawingId":"jacket","Value":"","SortValue":"","Drawing":"015E","Kind":"Noun","Category":"Clothes","PlaySessionLink":"","Tags":"","Complexity":"6","Gender":"","Form":"","Article":"","LinkedWord":"","Notes":"","Spanish":"CAMPERA","Italian":"GIACCA"},{"Id":"juice","Active":"1","Text":"JUICE","DrawingId":"juice","Value":"","SortValue":"","Drawing":"39","Kind":"Noun","Category":"Food","PlaySessionLink":"","Tags":"","Complexity":"5","Gender":"","Form":"","Article":"","LinkedWord":"","Notes":"","Spanish":"JUGO","Italian":"SUCCO"},{"Id":"kitchen","Active":"1","Text":"KITCHEN","DrawingId":"kitchen","Value":"","SortValue":"","Drawing":"015F","Kind":"Noun","Category":"Home","PlaySessionLink":"","Tags":"","Complexity":"7","Gender":"","Form":"","Article":"","LinkedWord":"","Notes":"","Spanish":"COCINA","Italian":"CUCINA"},{"Id":"knife","Active":"1","Text":"KNIFE","DrawingId":"knife","Value":"","SortValue":"","Drawing":"166","Kind":"Noun","Category":"Home","PlaySessionLink":"","Tags":"","Complexity":"5","Gender":"","Form":"","Article":"","LinkedWord":"","Notes":"","Spanish":"CUCHILLO","Italian":"COLTELLO"},{"Id":"lamp","Active":"1","Text":"LAMP","DrawingId":"lamp","Value":"","SortValue":"","Drawing":"167","Kind":"Noun","Category":"Home","PlaySessionLink":"","Tags":"","Complexity":"4","Gender":"","Form":"","Article":"","LinkedWord":"","Notes":"","Spanish":"LÁMPARA","Italian":"LAMPADA"},{"Id":"leg","Active":"1","Text":"LEG","DrawingId":"leg","Value":"","SortValue":"","Drawing":"CF","Kind":"Noun","Category":"Body","PlaySessionLink":"","Tags":"","Complexity":"3","Gender":"","Form":"","Article":"","LinkedWord":"","Notes":"","Spanish":"PIERNA","Italian":"GAMBA"},{"Id":"library","Active":"1","Text":"LIBRARY","DrawingId":"library","Value":"","SortValue":"","Drawing":"164","Kind":"Noun","Category":"City","PlaySessionLink":"","Tags":"","Complexity":"7","Gender":"","Form":"","Article":"","LinkedWord":"","Notes":"","Spanish":"BIBLIOTECA","Italian":"BIBLIOTECA"},{"Id":"lion","Active":"1","Text":"LION","DrawingId":"lion","Value":"","SortValue":"","Drawing":"D1","Kind":"Noun","Category":"Animals","PlaySessionLink":"","Tags":"","Complexity":"4","Gender":"","Form":"Singular","Article":"","LinkedWord":"","Notes":"","Spanish":"LEÓN","Italian":"LEONE"},{"Id":"lips","Active":"1","Text":"LIPS","DrawingId":"lips","Value":"","SortValue":"","Drawing":"2022","Kind":"Noun","Category":"Body","PlaySessionLink":"","Tags":"","Complexity":"4","Gender":"","Form":"","Article":"","LinkedWord":"","Notes":"","Spanish":"LABIOS","Italian":"LABBRA"},{"Id":"living_room","Active":"0","Text":"LIVING-ROOM","DrawingId":"","Value":"","SortValue":"","Drawing":"","Kind":"Noun","Category":"Home","PlaySessionLink":"","Tags":"","Complexity":"","Gender":"","Form":"","Article":"","LinkedWord":"","Notes":"","Spanish":"SALA","Italian":""},{"Id":"lizard","Active":"1","Text":"LIZARD","DrawingId":"lizard","Value":"","SortValue":"","Drawing":"147","Kind":"Noun","Category":"Animals","PlaySessionLink":"","Tags":"","Complexity":"6","Gender":"","Form":"","Article":"","LinkedWord":"","Notes":"","Spanish":"LAGARTIJA","Italian":"LUCERTOLA"},{"Id":"mall","Active":"0","Text":"MALL","DrawingId":"","Value":"","SortValue":"","Drawing":"","Kind":"Noun","Category":"City","PlaySessionLink":"","Tags":"","Complexity":"","Gender":"","Form":"","Article":"","LinkedWord":"","Notes":"","Spanish":"CENTRO COMERCIAL","Italian":""},{"Id":"man","Active":"1","Text":"MAN","DrawingId":"man","Value":"","SortValue":"","Drawing":"391","Kind":"Noun","Category":"Family","PlaySessionLink":"","Tags":"","Complexity":"3","Gender":"","Form":"","Article":"","LinkedWord":"","Notes":"","Spanish":"HOMBRE","Italian":"UOMO"},{"Id":"market","Active":"1","Text":"MARKET","DrawingId":"market","Value":"","SortValue":"","Drawing":"AB","Kind":"Noun","Category":"City","PlaySessionLink":"","Tags":"","Complexity":"6","Gender":"","Form":"","Article":"","LinkedWord":"","Notes":"","Spanish":"MERCADO","Italian":"MERCATO"},{"Id":"meat","Active":"1","Text":"MEAT","DrawingId":"meat","Value":"","SortValue":"","Drawing":"D3","Kind":"Noun","Category":"Food","PlaySessionLink":"","Tags":"","Complexity":"4","Gender":"","Form":"","Article":"","LinkedWord":"","Notes":"","Spanish":"CARNE","Italian":"CARNE"},{"Id":"mirror","Active":"1","Text":"MIRROR","DrawingId":"mirror","Value":"","SortValue":"","Drawing":"165","Kind":"Noun","Category":"Home","PlaySessionLink":"","Tags":"","Complexity":"6","Gender":"","Form":"","Article":"","LinkedWord":"","Notes":"","Spanish":"ESPEJO","Italian":"SPECCHIO"},{"Id":"monkey","Active":"1","Text":"MONKEY","DrawingId":"monkey","Value":"","SortValue":"","Drawing":"1EAA","Kind":"Noun","Category":"Animals","PlaySessionLink":"","Tags":"","Complexity":"6","Gender":"","Form":"","Article":"","LinkedWord":"","Notes":"","Spanish":"MONO","Italian":"SCIMMIA"},{"Id":"month_april","Active":"1","Text":"APRIL","DrawingId":"month_april","Value":"4","SortValue":"4","Drawing":"2264","Kind":"Noun","Category":"Months","PlaySessionLink":"","Tags":"","Complexity":"5","Gender":"","Form":"","Article":"","LinkedWord":"","Notes":"","Spanish":"ABRIL","Italian":"APRILE"},{"Id":"month_august","Active":"1","Text":"AUGUST","DrawingId":"month_august","Value":"8","SortValue":"8","Drawing":"B1","Kind":"Noun","Category":"Months","PlaySessionLink":"","Tags":"","Complexity":"6","Gender":"","Form":"","Article":"","LinkedWord":"","Notes":"","Spanish":"AGOSTO","Italian":"AGOSTO"},{"Id":"month_december","Active":"1","Text":"DECEMBER","DrawingId":"month_december","Value":"12","SortValue":"12","Drawing":"2248","Kind":"Noun","Category":"Months","PlaySessionLink":"","Tags":"","Complexity":"8","Gender":"","Form":"","Article":"","LinkedWord":"","Notes":"","Spanish":"DICIEMBRE","Italian":"DICEMBRE"},{"Id":"month_february","Active":"1","Text":"FEBRUARY","DrawingId":"month_february","Value":"2","SortValue":"2","Drawing":"7E","Kind":"Noun","Category":"Months","PlaySessionLink":"","Tags":"","Complexity":"8","Gender":"","Form":"","Article":"","LinkedWord":"","Notes":"","Spanish":"FEBRERO","Italian":"FEBBRAIO"},{"Id":"month_january","Active":"1","Text":"JANUARY","DrawingId":"month_january","Value":"1","SortValue":"1","Drawing":"AC","Kind":"Noun","Category":"Months","PlaySessionLink":"","Tags":"","Complexity":"7","Gender":"","Form":"","Article":"","LinkedWord":"","Notes":"","Spanish":"ENERO","Italian":"GENNAIO"},{"Id":"month_july","Active":"1","Text":"JULY","DrawingId":"month_july","Value":"7","SortValue":"7","Drawing":"2205","Kind":"Noun","Category":"Months","PlaySessionLink":"","Tags":"","Complexity":"4","Gender":"","Form":"","Article":"","LinkedWord":"","Notes":"","Spanish":"JULIO","Italian":"LUGLIO"},{"Id":"month_june","Active":"1","Text":"JUNE","DrawingId":"month_june","Value":"6","SortValue":"6","Drawing":"221E","Kind":"Noun","Category":"Months","PlaySessionLink":"","Tags":"","Complexity":"4","Gender":"","Form":"","Article":"","LinkedWord":"","Notes":"","Spanish":"JUNIO","Italian":"GIUGNO"},{"Id":"month_march","Active":"1","Text":"MARCH","DrawingId":"month_march","Value":"3","SortValue":"3","Drawing":"222B","Kind":"Noun","Category":"Months","PlaySessionLink":"","Tags":"","Complexity":"5","Gender":"","Form":"","Article":"","LinkedWord":"","Notes":"","Spanish":"MARZO","Italian":"MARZO"},{"Id":"month_may","Active":"1","Text":"MAY","DrawingId":"month_may","Value":"5","SortValue":"5","Drawing":"220F","Kind":"Noun","Category":"Months","PlaySessionLink":"","Tags":"","Complexity":"3","Gender":"","Form":"","Article":"","LinkedWord":"","Notes":"","Spanish":"MAYO","Italian":"MAGGIO"},{"Id":"month_november","Active":"1","Text":"NOVEMBER","DrawingId":"month_november","Value":"11","SortValue":"11","Drawing":"2211","Kind":"Noun","Category":"Months","PlaySessionLink":"","Tags":"","Complexity":"8","Gender":"","Form":"","Article":"","LinkedWord":"","Notes":"","Spanish":"NOVIEMBRE","Italian":"NOVEMBRE"},{"Id":"month_october","Active":"1","Text":"OCTOBER","DrawingId":"month_october","Value":"10","SortValue":"10","Drawing":"221A","Kind":"Noun","Category":"Months","PlaySessionLink":"","Tags":"","Complexity":"7","Gender":"","Form":"","Article":"","LinkedWord":"","Notes":"","Spanish":"OCTUBRE","Italian":"OTTOBRE"},{"Id":"month_september","Active":"1","Text":"SEPTEMBER","DrawingId":"month_september","Value":"9","SortValue":"9","Drawing":"2202","Kind":"Noun","Category":"Months","PlaySessionLink":"","Tags":"","Complexity":"9","Gender":"","Form":"","Article":"","LinkedWord":"","Notes":"","Spanish":"SEPTIEMBRE","Italian":"SETTEMBRE"},{"Id":"moon","Active":"1","Text":"MOON","DrawingId":"moon","Value":"","SortValue":"","Drawing":"D4","Kind":"Noun","Category":"Nature","PlaySessionLink":"","Tags":"","Complexity":"4","Gender":"","Form":"","Article":"","LinkedWord":"","Notes":"","Spanish":"LUNA","Italian":"LUNA"},{"Id":"mother","Active":"1","Text":"MOTHER","DrawingId":"mother","Value":"","SortValue":"","Drawing":"D6","Kind":"Noun","Category":"Family","PlaySessionLink":"","Tags":"","Complexity":"6","Gender":"","Form":"","Article":"","LinkedWord":"","Notes":"","Spanish":"MADRE","Italian":"MADRE"},{"Id":"motorbike","Active":"1","Text":"MOTORBIKE","DrawingId":"motorbike","Value":"","SortValue":"","Drawing":"162","Kind":"Noun","Category":"City","PlaySessionLink":"","Tags":"","Complexity":"9","Gender":"","Form":"","Article":"","LinkedWord":"","Notes":"","Spanish":"MOTO","Italian":"MOTO"},{"Id":"mountain","Active":"1","Text":"MOUNTAIN","DrawingId":"mountain","Value":"","SortValue":"","Drawing":"D2","Kind":"Noun","Category":"Nature","PlaySessionLink":"","Tags":"","Complexity":"8","Gender":"","Form":"","Article":"","LinkedWord":"","Notes":"","Spanish":"MONTAÑA","Italian":"MONTAGNA"},{"Id":"mouth","Active":"1","Text":"MOUTH","DrawingId":"mouth","Value":"","SortValue":"","Drawing":"D5","Kind":"Noun","Category":"Body","PlaySessionLink":"","Tags":"","Complexity":"5","Gender":"","Form":"","Article":"","LinkedWord":"","Notes":"","Spanish":"BOCA","Italian":"BOCCA"},{"Id":"museum","Active":"1","Text":"MUSEUM","DrawingId":"museum","Value":"","SortValue":"","Drawing":"163","Kind":"Noun","Category":"City","PlaySessionLink":"","Tags":"","Complexity":"6","Gender":"","Form":"","Article":"","LinkedWord":"","Notes":"","Spanish":"MUSEO","Italian":"MUSEO"},{"Id":"nail","Active":"1","Text":"NAIL","DrawingId":"nail","Value":"","SortValue":"","Drawing":"152","Kind":"Noun","Category":"Body","PlaySessionLink":"","Tags":"","Complexity":"4","Gender":"","Form":"","Article":"","LinkedWord":"","Notes":"","Spanish":"UÑA","Italian":"UNGHIA"},{"Id":"needle","Active":"1","Text":"NEEDLE","DrawingId":"needle","Value":"","SortValue":"","Drawing":"DE","Kind":"Noun","Category":"Objects","PlaySessionLink":"","Tags":"","Complexity":"6","Gender":"","Form":"","Article":"","LinkedWord":"","Notes":"","Spanish":"AGUJA","Italian":"AGO"},{"Id":"nose","Active":"1","Text":"NOSE","DrawingId":"nose","Value":"","SortValue":"","Drawing":"DB","Kind":"Noun","Category":"Body","PlaySessionLink":"","Tags":"","Complexity":"4","Gender":"","Form":"","Article":"","LinkedWord":"","Notes":"","Spanish":"NARIZ","Italian":"NASO"},{"Id":"number_00","Active":"1","Text":"ZERO","DrawingId":"number_00","Value":"0","SortValue":"0","Drawing":"2669","Kind":"Noun","Category":"Numbers","PlaySessionLink":"","Tags":"","Complexity":"4","Gender":"","Form":"Singular","Article":"","LinkedWord":"","Notes":"","Spanish":"CERO","Italian":"ZERO"},{"Id":"number_01","Active":"1","Text":"ONE","DrawingId":"number_01","Value":"1","SortValue":"1","Drawing":"266A","Kind":"Noun","Category":"Numbers","PlaySessionLink":"","Tags":"","Complexity":"3","Gender":"","Form":"Singular","Article":"","LinkedWord":"","Notes":"","Spanish":"UNO","Italian":"UNO"},{"Id":"number_02","Active":"1","Text":"TWO","DrawingId":"number_02","Value":"2","SortValue":"2","Drawing":"266B","Kind":"Noun","Category":"Numbers","PlaySessionLink":"","Tags":"","Complexity":"3","Gender":"","Form":"Singular","Article":"","LinkedWord":"","Notes":"","Spanish":"DOS","Italian":"DUE"},{"Id":"number_03","Active":"1","Text":"THREE","DrawingId":"number_03","Value":"3","SortValue":"3","Drawing":"266C","Kind":"Noun","Category":"Numbers","PlaySessionLink":"","Tags":"","Complexity":"5","Gender":"","Form":"Singular","Article":"","LinkedWord":"","Notes":"","Spanish":"TRES","Italian":"TRE"},{"Id":"number_04","Active":"1","Text":"FOUR","DrawingId":"number_04","Value":"4","SortValue":"4","Drawing":"266D","Kind":"Noun","Category":"Numbers","PlaySessionLink":"","Tags":"","Complexity":"4","Gender":"","Form":"Singular","Article":"","LinkedWord":"","Notes":"","Spanish":"CUATRO","Italian":"QUATTRO"},{"Id":"number_05","Active":"1","Text":"FIVE","DrawingId":"number_05","Value":"5","SortValue":"5","Drawing":"266E","Kind":"Noun","Category":"Numbers","PlaySessionLink":"","Tags":"","Complexity":"4","Gender":"","Form":"Singular","Article":"","LinkedWord":"","Notes":"","Spanish":"CINCO","Italian":"CINQUE"},{"Id":"number_06","Active":"1","Text":"SIX","DrawingId":"number_06","Value":"6","SortValue":"6","Drawing":"266F","Kind":"Noun","Category":"Numbers","PlaySessionLink":"","Tags":"","Complexity":"3","Gender":"","Form":"Singular","Article":"","LinkedWord":"","Notes":"","Spanish":"SEIS","Italian":"SEI"},{"Id":"number_07","Active":"1","Text":"SEVEN","DrawingId":"number_07","Value":"7","SortValue":"7","Drawing":"10E","Kind":"Noun","Category":"Numbers","PlaySessionLink":"","Tags":"","Complexity":"5","Gender":"","Form":"Singular","Article":"","LinkedWord":"","Notes":"","Spanish":"SIETE","Italian":"SETTE"},{"Id":"number_08","Active":"1","Text":"EIGHT","DrawingId":"number_08","Value":"8","SortValue":"8","Drawing":"122","Kind":"Noun","Category":"Numbers","PlaySessionLink":"","Tags":"","Complexity":"5","Gender":"","Form":"Singular","Article":"","LinkedWord":"","Notes":"","Spanish":"OCHO","Italian":"OTTO"},{"Id":"number_09","Active":"1","Text":"NINE","DrawingId":"number_09","Value":"9","SortValue":"9","Drawing":"12A","Kind":"Noun","Category":"Numbers","PlaySessionLink":"","Tags":"","Complexity":"4","Gender":"","Form":"Singular","Article":"","LinkedWord":"","Notes":"","Spanish":"NUEVE","Italian":"NOVE"},{"Id":"number_10","Active":"1","Text":"TEN","DrawingId":"number_10","Value":"10","SortValue":"10","Drawing":"12E","Kind":"Noun","Category":"Numbers","PlaySessionLink":"","Tags":"","Complexity":"3","Gender":"","Form":"Singular","Article":"","LinkedWord":"","Notes":"","Spanish":"DIEZ","Italian":"DIECI"},{"Id":"number_11","Active":"1","Text":"ELEVEN","DrawingId":"number_11","Value":"11","SortValue":"11","Drawing":"136","Kind":"Noun","Category":"Numbers","PlaySessionLink":"","Tags":"","Complexity":"6","Gender":"","Form":"Singular","Article":"","LinkedWord":"","Notes":"","Spanish":"ONCE","Italian":"UNDICI"},{"Id":"number_12","Active":"1","Text":"TWELVE","DrawingId":"number_12","Value":"12","SortValue":"12","Drawing":"14A","Kind":"Noun","Category":"Numbers","PlaySessionLink":"","Tags":"","Complexity":"6","Gender":"","Form":"Singular","Article":"","LinkedWord":"","Notes":"","Spanish":"DOCE","Italian":"DODICI"},{"Id":"number_13","Active":"1","Text":"THIRTEEN","DrawingId":"number_13","Value":"13","SortValue":"13","Drawing":"103","Kind":"Noun","Category":"Numbers","PlaySessionLink":"","Tags":"","Complexity":"8","Gender":"","Form":"Singular","Article":"","LinkedWord":"","Notes":"","Spanish":"TRECE","Italian":"TREDICI"},{"Id":"number_14","Active":"1","Text":"FOURTEEN","DrawingId":"number_14","Value":"14","SortValue":"14","Drawing":"10F","Kind":"Noun","Category":"Numbers","PlaySessionLink":"","Tags":"","Complexity":"8","Gender":"","Form":"Singular","Article":"","LinkedWord":"","Notes":"","Spanish":"CATORCE","Italian":"QUATTORDICI"},{"Id":"number_15","Active":"1","Text":"FIFTEEN","DrawingId":"number_15","Value":"15","SortValue":"15","Drawing":"113","Kind":"Noun","Category":"Numbers","PlaySessionLink":"","Tags":"","Complexity":"7","Gender":"","Form":"Singular","Article":"","LinkedWord":"","Notes":"","Spanish":"QUINCE","Italian":"QUINDICI"},{"Id":"number_16","Active":"1","Text":"SIXTEEN","DrawingId":"number_16","Value":"16","SortValue":"16","Drawing":"119","Kind":"Noun","Category":"Numbers","PlaySessionLink":"","Tags":"","Complexity":"7","Gender":"","Form":"Singular","Article":"","LinkedWord":"","Notes":"","Spanish":"DIECISÉIS","Italian":"SEDICI"},{"Id":"number_17","Active":"1","Text":"SEVENTEEN","DrawingId":"number_17","Value":"17","SortValue":"17","Drawing":"123","Kind":"Noun","Category":"Numbers","PlaySessionLink":"","Tags":"","Complexity":"9","Gender":"","Form":"Singular","Article":"","LinkedWord":"","Notes":"","Spanish":"DIECISIETE","Italian":"DICIASSETTE"},{"Id":"number_18","Active":"1","Text":"EIGHTEEN","DrawingId":"number_18","Value":"18","SortValue":"18","Drawing":"12B","Kind":"Noun","Category":"Numbers","PlaySessionLink":"","Tags":"","Complexity":"8","Gender":"","Form":"Singular","Article":"","LinkedWord":"","Notes":"","Spanish":"DIECIOCHO","Italian":"DICIOTTO"},{"Id":"number_19","Active":"1","Text":"NINETEEN","DrawingId":"number_19","Value":"19","SortValue":"19","Drawing":"12F","Kind":"Noun","Category":"Numbers","PlaySessionLink":"","Tags":"","Complexity":"8","Gender":"","Form":"Singular","Article":"","LinkedWord":"","Notes":"","Spanish":"DIECINUEVE","Italian":"DICIANNOVE"},{"Id":"number_20","Active":"1","Text":"TWENTY","DrawingId":"number_20","Value":"20","SortValue":"20","Drawing":"137","Kind":"Noun","Category":"Numbers","PlaySessionLink":"","Tags":"","Complexity":"6","Gender":"","Form":"Singular","Article":"","LinkedWord":"","Notes":"","Spanish":"VEINTE","Italian":"VENTI"},{"Id":"octopus","Active":"1","Text":"OCTOPUS","DrawingId":"octopus","Value":"","SortValue":"","Drawing":"170","Kind":"Noun","Category":"Animals","PlaySessionLink":"","Tags":"","Complexity":"7","Gender":"","Form":"Singular","Article":"","LinkedWord":"","Notes":"","Spanish":"PULPO","Italian":"POLPO"},{"Id":"oil","Active":"1","Text":"OIL","DrawingId":"oil","Value":"","SortValue":"","Drawing":"D9","Kind":"Noun","Category":"Food","PlaySessionLink":"","Tags":"","Complexity":"3","Gender":"","Form":"","Article":"","LinkedWord":"","Notes":"","Spanish":"ACEITE","Italian":"OLIO"},{"Id":"onion","Active":"1","Text":"ONION","DrawingId":"onion","Value":"","SortValue":"","Drawing":"DD","Kind":"Noun","Category":"Food","PlaySessionLink":"","Tags":"","Complexity":"5","Gender":"","Form":"","Article":"","LinkedWord":"","Notes":"","Spanish":"CEBOLLA","Italian":"CIPOLLA"},{"Id":"oven","Active":"1","Text":"OVEN","DrawingId":"oven","Value":"","SortValue":"","Drawing":"A7","Kind":"Noun","Category":"Home","PlaySessionLink":"","Tags":"","Complexity":"4","Gender":"","Form":"","Article":"","LinkedWord":"","Notes":"","Spanish":"HORNO","Italian":"FORNO"},{"Id":"paper","Active":"1","Text":"PAPER","DrawingId":"paper","Value":"","SortValue":"","Drawing":"171","Kind":"Noun","Category":"Objects","PlaySessionLink":"","Tags":"","Complexity":"5","Gender":"","Form":"","Article":"","LinkedWord":"","Notes":"","Spanish":"PAPEL","Italian":"CARTA"},{"Id":"park","Active":"1","Text":"PARK","DrawingId":"park","Value":"","SortValue":"","Drawing":"016A","Kind":"Noun","Category":"City","PlaySessionLink":"","Tags":"","Complexity":"4","Gender":"","Form":"","Article":"","LinkedWord":"","Notes":"","Spanish":"PARQUE","Italian":"PARCO"},{"Id":"parrot","Active":"1","Text":"PARROT","DrawingId":"parrot","Value":"","SortValue":"","Drawing":"E2","Kind":"Noun","Category":"Animals","PlaySessionLink":"","Tags":"","Complexity":"6","Gender":"","Form":"","Article":"","LinkedWord":"","Notes":"","Spanish":"LORO","Italian":"PAPPAGALLO"},{"Id":"pear","Active":"1","Text":"PEAR","DrawingId":"pear","Value":"","SortValue":"","Drawing":"E4","Kind":"Noun","Category":"Food","PlaySessionLink":"","Tags":"","Complexity":"4","Gender":"","Form":"","Article":"","LinkedWord":"","Notes":"","Spanish":"PERA","Italian":"PERA"},{"Id":"pencil","Active":"1","Text":"PENCIL","DrawingId":"pencil","Value":"","SortValue":"","Drawing":"E5","Kind":"Noun","Category":"Objects","PlaySessionLink":"","Tags":"","Complexity":"6","Gender":"","Form":"","Article":"","LinkedWord":"","Notes":"","Spanish":"LÁPIZ","Italian":"MATITA"},{"Id":"penguin","Active":"1","Text":"PENGUIN","DrawingId":"penguin","Value":"","SortValue":"","Drawing":"016B","Kind":"Noun","Category":"Animals","PlaySessionLink":"","Tags":"","Complexity":"7","Gender":"","Form":"","Article":"","LinkedWord":"","Notes":"","Spanish":"PINGÜINO","Italian":"PINGUINO"},{"Id":"pepper","Active":"1","Text":"PEPPER","DrawingId":"pepper","Value":"","SortValue":"","Drawing":"172","Kind":"Noun","Category":"Food","PlaySessionLink":"","Tags":"","Complexity":"6","Gender":"","Form":"","Article":"","LinkedWord":"","Notes":"","Spanish":"MORRÓN","Italian":"PEPERONE"},{"Id":"pet","Active":"1","Text":"PET","DrawingId":"pet","Value":"","SortValue":"","Drawing":"173","Kind":"Noun","Category":"Family","PlaySessionLink":"","Tags":"","Complexity":"3","Gender":"","Form":"","Article":"","LinkedWord":"","Notes":"","Spanish":"MASCOTA","Italian":"ANIMALE DOMESTICO"},{"Id":"pharmacy","Active":"1","Text":"PHARMACY","DrawingId":"pharmacy","Value":"","SortValue":"","Drawing":"016E","Kind":"Noun","Category":"City","PlaySessionLink":"","Tags":"","Complexity":"8","Gender":"","Form":"","Article":"","LinkedWord":"","Notes":"","Spanish":"FARMACIA","Italian":"FARMACIA"},{"Id":"pig","Active":"1","Text":"PIG","DrawingId":"pig","Value":"","SortValue":"","Drawing":"016F","Kind":"Noun","Category":"Animals","PlaySessionLink":"","Tags":"","Complexity":"3","Gender":"","Form":"","Article":"","LinkedWord":"","Notes":"","Spanish":"CHANCHO","Italian":"MAIALE"},{"Id":"plane","Active":"1","Text":"PLANE","DrawingId":"plane","Value":"","SortValue":"","Drawing":"179","Kind":"Noun","Category":"City","PlaySessionLink":"","Tags":"","Complexity":"5","Gender":"","Form":"","Article":"","LinkedWord":"","Notes":"","Spanish":"AVIÓN","Italian":"AEREO"},{"Id":"plant","Active":"1","Text":"PLANT","DrawingId":"plant","Value":"","SortValue":"","Drawing":"017A","Kind":"Noun","Category":"Nature","PlaySessionLink":"","Tags":"","Complexity":"5","Gender":"","Form":"","Article":"","LinkedWord":"","Notes":"","Spanish":"PLANTA","Italian":"PIANTA"},{"Id":"playground","Active":"1","Text":"PLAYGROUND","DrawingId":"playground","Value":"","SortValue":"","Drawing":"11A","Kind":"Noun","Category":"City","PlaySessionLink":"","Tags":"","Complexity":"10","Gender":"","Form":"","Article":"","LinkedWord":"","Notes":"","Spanish":"PARQUE INFANTIL","Italian":"PARCO GIOCHI"},{"Id":"port","Active":"1","Text":"PORT","DrawingId":"port","Value":"","SortValue":"","Drawing":"017D","Kind":"Noun","Category":"City","PlaySessionLink":"","Tags":"","Complexity":"4","Gender":"","Form":"","Article":"","LinkedWord":"","Notes":"","Spanish":"PUERTO","Italian":"PORTO"},{"Id":"potato","Active":"1","Text":"POTATO","DrawingId":"potato","Value":"","SortValue":"","Drawing":"E7","Kind":"Noun","Category":"Food","PlaySessionLink":"","Tags":"","Complexity":"6","Gender":"","Form":"Singular","Article":"","LinkedWord":"","Notes":"","Spanish":"PAPA","Italian":"PATATA"},{"Id":"rain","Active":"1","Text":"RAIN","DrawingId":"rain","Value":"","SortValue":"","Drawing":"F0","Kind":"Noun","Category":"Nature","PlaySessionLink":"","Tags":"","Complexity":"4","Gender":"","Form":"","Article":"","LinkedWord":"","Notes":"","Spanish":"LLUVIA","Italian":"PIOGGIA"},{"Id":"rat","Active":"1","Text":"RAT","DrawingId":"rat","Value":"","SortValue":"","Drawing":"D8","Kind":"Noun","Category":"Animals","PlaySessionLink":"","Tags":"","Complexity":"3","Gender":"","Form":"","Article":"","LinkedWord":"","Notes":"","Spanish":"RATA","Italian":"TOPO"},{"Id":"restaurant","Active":"1","Text":"RESTAURANT","DrawingId":"restaurant","Value":"","SortValue":"","Drawing":"26","Kind":"Noun","Category":"City","PlaySessionLink":"","Tags":"","Complexity":"10","Gender":"","Form":"","Article":"","LinkedWord":"","Notes":"","Spanish":"RESTAURANTE","Italian":"RISTORANTE"},{"Id":"rice","Active":"1","Text":"RICE","DrawingId":"rice","Value":"","SortValue":"","Drawing":"E9","Kind":"Noun","Category":"Food","PlaySessionLink":"","Tags":"","Complexity":"4","Gender":"","Form":"","Article":"","LinkedWord":"","Notes":"","Spanish":"ARROZ","Italian":"RISO"},{"Id":"river","Active":"1","Text":"RIVER","DrawingId":"river","Value":"","SortValue":"","Drawing":"EA","Kind":"Noun","Category":"Nature","PlaySessionLink":"","Tags":"","Complexity":"5","Gender":"","Form":"","Article":"","LinkedWord":"","Notes":"","Spanish":"RÍO","Italian":"FIUME"},{"Id":"road","Active":"1","Text":"ROAD","DrawingId":"road","Value":"","SortValue":"","Drawing":"145","Kind":"Noun","Category":"City","PlaySessionLink":"","Tags":"","Complexity":"4","Gender":"","Form":"","Article":"","LinkedWord":"","Notes":"","Spanish":"CARRETERA","Italian":"STRADA"},{"Id":"roof","Active":"1","Text":"ROOF","DrawingId":"roof","Value":"","SortValue":"","Drawing":"017E","Kind":"Noun","Category":"Home","PlaySessionLink":"","Tags":"","Complexity":"4","Gender":"","Form":"","Article":"","LinkedWord":"","Notes":"","Spanish":"TECHO","Italian":"TETTO"},{"Id":"salt","Active":"1","Text":"SALT","DrawingId":"salt","Value":"","SortValue":"","Drawing":"EB","Kind":"Noun","Category":"Food","PlaySessionLink":"","Tags":"","Complexity":"4","Gender":"","Form":"","Article":"","LinkedWord":"","Notes":"","Spanish":"SAL","Italian":"SALE"},{"Id":"scarf","Active":"1","Text":"SCARF","DrawingId":"scarf","Value":"","SortValue":"","Drawing":"017B","Kind":"Noun","Category":"Clothes","PlaySessionLink":"","Tags":"","Complexity":"5","Gender":"","Form":"","Article":"","LinkedWord":"","Notes":"","Spanish":"BUFANDA","Italian":"SCIARPA"},{"Id":"school","Active":"1","Text":"SCHOOL","DrawingId":"school","Value":"","SortValue":"","Drawing":"2196","Kind":"Noun","Category":"City","PlaySessionLink":"","Tags":"","Complexity":"6","Gender":"","Form":"","Article":"","LinkedWord":"","Notes":"","Spanish":"ESCUELA","Italian":"SCUOLA"},{"Id":"scissors","Active":"1","Text":"SCISSORS","DrawingId":"scissors","Value":"","SortValue":"","Drawing":"E8","Kind":"Noun","Category":"Objects","PlaySessionLink":"","Tags":"","Complexity":"8","Gender":"","Form":"","Article":"","LinkedWord":"","Notes":"","Spanish":"TIJERAS","Italian":"FORBICI"},{"Id":"sea","Active":"1","Text":"SEA","DrawingId":"sea","Value":"","SortValue":"","Drawing":"150","Kind":"Noun","Category":"Nature","PlaySessionLink":"","Tags":"","Complexity":"3","Gender":"","Form":"","Article":"","LinkedWord":"","Notes":"","Spanish":"MAR","Italian":"MARE"},{"Id":"shirt","Active":"1","Text":"SHIRT","DrawingId":"shirt","Value":"","SortValue":"","Drawing":"ED","Kind":"Noun","Category":"Clothes","PlaySessionLink":"","Tags":"","Complexity":"5","Gender":"","Form":"","Article":"","LinkedWord":"","Notes":"","Spanish":"CAMISA","Italian":"CAMICIA"},{"Id":"shoes","Active":"1","Text":"SHOES","DrawingId":"shoes","Value":"","SortValue":"","Drawing":"112","Kind":"Noun","Category":"Clothes","PlaySessionLink":"","Tags":"","Complexity":"5","Gender":"","Form":"","Article":"","LinkedWord":"","Notes":"","Spanish":"ZAPATOS","Italian":"SCARPE"},{"Id":"shop","Active":"1","Text":"SHOP","DrawingId":"shop","Value":"","SortValue":"","Drawing":"2198","Kind":"Noun","Category":"City","PlaySessionLink":"","Tags":"","Complexity":"4","Gender":"","Form":"","Article":"","LinkedWord":"","Notes":"","Spanish":"TIENDA","Italian":"NEGOZIO"},{"Id":"shower","Active":"1","Text":"SHOWER","DrawingId":"shower","Value":"","SortValue":"","Drawing":"017C","Kind":"Noun","Category":"Home","PlaySessionLink":"","Tags":"","Complexity":"6","Gender":"","Form":"","Article":"","LinkedWord":"","Notes":"","Spanish":"DUCHA","Italian":"DOCCIA"},{"Id":"sink","Active":"1","Text":"SINK","DrawingId":"sink","Value":"","SortValue":"","Drawing":"1EA5","Kind":"Noun","Category":"Home","PlaySessionLink":"","Tags":"","Complexity":"4","Gender":"","Form":"","Article":"","LinkedWord":"","Notes":"","Spanish":"PILETA","Italian":"LAVANDINO"},{"Id":"sister","Active":"1","Text":"SISTER","DrawingId":"sister","Value":"","SortValue":"","Drawing":"EE","Kind":"Noun","Category":"Family","PlaySessionLink":"","Tags":"","Complexity":"6","Gender":"","Form":"","Article":"","LinkedWord":"","Notes":"","Spanish":"HERMANA","Italian":"SORELLA"},{"Id":"skirt","Active":"1","Text":"SKIRT","DrawingId":"skirt","Value":"","SortValue":"","Drawing":"1EA4","Kind":"Noun","Category":"Clothes","PlaySessionLink":"","Tags":"","Complexity":"5","Gender":"","Form":"","Article":"","LinkedWord":"","Notes":"","Spanish":"POLLERA","Italian":"GONNA"},{"Id":"sky","Active":"1","Text":"SKY","DrawingId":"sky","Value":"","SortValue":"","Drawing":"2026","Kind":"Noun","Category":"Nature","PlaySessionLink":"","Tags":"","Complexity":"3","Gender":"","Form":"","Article":"","LinkedWord":"","Notes":"","Spanish":"CIELO","Italian":"CIELO"},{"Id":"snake","Active":"1","Text":"SNAKE","DrawingId":"snake","Value":"","SortValue":"","Drawing":"011E","Kind":"Noun","Category":"Animals","PlaySessionLink":"","Tags":"","Complexity":"5","Gender":"","Form":"","Article":"","LinkedWord":"","Notes":"","Spanish":"SERPIENTE","Italian":"SERPENTE"},{"Id":"snow","Active":"1","Text":"SNOW","DrawingId":"snow","Value":"","SortValue":"","Drawing":"EF","Kind":"Noun","Category":"Nature","PlaySessionLink":"","Tags":"","Complexity":"4","Gender":"","Form":"","Article":"","LinkedWord":"","Notes":"","Spanish":"NIEVE","Italian":"NEVE"},{"Id":"soap","Active":"1","Text":"SOAP","DrawingId":"soap","Value":"","SortValue":"","Drawing":"14C","Kind":"Noun","Category":"Home","PlaySessionLink":"","Tags":"","Complexity":"4","Gender":"","Form":"","Article":"","LinkedWord":"","Notes":"","Spanish":"JABÓN","Italian":"SAPONE"},{"Id":"socks","Active":"1","Text":"SOCKS","DrawingId":"socks","Value":"","SortValue":"","Drawing":"011F","Kind":"Noun","Category":"Clothes","PlaySessionLink":"","Tags":"","Complexity":"5","Gender":"","Form":"","Article":"","LinkedWord":"","Notes":"","Spanish":"MEDIAS","Italian":"CALZINI"},{"Id":"son","Active":"1","Text":"SON","DrawingId":"son","Value":"","SortValue":"","Drawing":"98","Kind":"Noun","Category":"Family","PlaySessionLink":"","Tags":"","Complexity":"3","Gender":"","Form":"","Article":"","LinkedWord":"","Notes":"","Spanish":"HIJO","Italian":"FIGLIO"},{"Id":"spoon","Active":"1","Text":"SPOON","DrawingId":"spoon","Value":"","SortValue":"","Drawing":"120","Kind":"Noun","Category":"Home","PlaySessionLink":"","Tags":"","Complexity":"5","Gender":"","Form":"","Article":"","LinkedWord":"","Notes":"","Spanish":"CUCHARA","Italian":"CUCCHIAIO"},{"Id":"spring","Active":"1","Text":"SPRING","DrawingId":"spring","Value":"1","SortValue":"1","Drawing":"2192","Kind":"Noun","Category":"Seasons","PlaySessionLink":"","Tags":"","Complexity":"6","Gender":"","Form":"","Article":"","LinkedWord":"","Notes":"","Spanish":"PRIMAVERA","Italian":"PRIMAVERA"},{"Id":"squirrel","Active":"1","Text":"SQUIRREL","DrawingId":"squirrel","Value":"","SortValue":"","Drawing":"154","Kind":"Noun","Category":"Animals","PlaySessionLink":"","Tags":"","Complexity":"8","Gender":"","Form":"","Article":"","LinkedWord":"","Notes":"","Spanish":"ARDILLA","Italian":"SCOIATTOLO"},{"Id":"stairs","Active":"1","Text":"STAIRS","DrawingId":"stairs","Value":"","SortValue":"","Drawing":"121","Kind":"Noun","Category":"Home","PlaySessionLink":"","Tags":"","Complexity":"6","Gender":"","Form":"","Article":"","LinkedWord":"","Notes":"","Spanish":"ESCALERA","Italian":"SCALE"},{"Id":"star","Active":"1","Text":"STAR","DrawingId":"star","Value":"","SortValue":"","Drawing":"13A","Kind":"Noun","Category":"Nature","PlaySessionLink":"","Tags":"","Complexity":"4","Gender":"","Form":"","Article":"","LinkedWord":"","Notes":"","Spanish":"ESTRELLA","Italian":"STELLA"},{"Id":"station","Active":"1","Text":"STATION","DrawingId":"station","Value":"","SortValue":"","Drawing":"2197","Kind":"Noun","Category":"City","PlaySessionLink":"","Tags":"","Complexity":"7","Gender":"","Form":"","Article":"","LinkedWord":"","Notes":"","Spanish":"ESTACIÓN","Italian":"STAZIONE"},{"Id":"stone","Active":"1","Text":"STONE","DrawingId":"stone","Value":"","SortValue":"","Drawing":"126","Kind":"Noun","Category":"Nature","PlaySessionLink":"","Tags":"","Complexity":"5","Gender":"","Form":"","Article":"","LinkedWord":"","Notes":"","Spanish":"PIEDRA","Italian":"PIETRA"},{"Id":"stove","Active":"1","Text":"STOVE","DrawingId":"stove","Value":"","SortValue":"","Drawing":"127","Kind":"Noun","Category":"Home","PlaySessionLink":"","Tags":"","Complexity":"5","Gender":"","Form":"","Article":"","LinkedWord":"","Notes":"","Spanish":"ESTUFA","Italian":"STUFA"},{"Id":"street","Active":"1","Text":"STREET","DrawingId":"street","Value":"","SortValue":"","Drawing":"131","Kind":"Noun","Category":"City","PlaySessionLink":"","Tags":"","Complexity":"6","Gender":"","Form":"","Article":"","LinkedWord":"","Notes":"","Spanish":"CALLE","Italian":"VIA"},{"Id":"sugar","Active":"1","Text":"SUGAR","DrawingId":"sugar","Value":"","SortValue":"","Drawing":"2191","Kind":"Noun","Category":"Food","PlaySessionLink":"","Tags":"","Complexity":"5","Gender":"","Form":"","Article":"","LinkedWord":"","Notes":"","Spanish":"AZÚCAR","Italian":"ZUCCHERO"},{"Id":"summer","Active":"1","Text":"SUMMER","DrawingId":"summer","Value":"2","SortValue":"2","Drawing":"2030","Kind":"Noun","Category":"Seasons","PlaySessionLink":"","Tags":"","Complexity":"6","Gender":"","Form":"","Article":"","LinkedWord":"","Notes":"","Spanish":"VERANO","Italian":"ESTATE"},{"Id":"sun","Active":"1","Text":"SUN","DrawingId":"sun","Value":"","SortValue":"","Drawing":"F1","Kind":"Noun","Category":"Nature","PlaySessionLink":"","Tags":"","Complexity":"3","Gender":"","Form":"","Article":"","LinkedWord":"","Notes":"","Spanish":"SOL","Italian":"SOLE"},{"Id":"t-shirt","Active":"0","Text":"T-SHIRT","DrawingId":"","Value":"","SortValue":"","Drawing":"","Kind":"Noun","Category":"Clothes","PlaySessionLink":"","Tags":"","Complexity":"","Gender":"","Form":"","Article":"","LinkedWord":"","Notes":"","Spanish":"CAMISETA","Italian":""},{"Id":"table","Active":"1","Text":"TABLE","DrawingId":"table","Value":"","SortValue":"","Drawing":"F3","Kind":"Noun","Category":"Home","PlaySessionLink":"","Tags":"","Complexity":"5","Gender":"","Form":"","Article":"","LinkedWord":"","Notes":"","Spanish":"MESA","Italian":"TAVOLO"},{"Id":"tea","Active":"1","Text":"TEA","DrawingId":"tea","Value":"","SortValue":"","Drawing":"F4","Kind":"Noun","Category":"Food","PlaySessionLink":"","Tags":"","Complexity":"3","Gender":"","Form":"","Article":"","LinkedWord":"","Notes":"","Spanish":"TÉ","Italian":"TÈ"},{"Id":"tear","Active":"1","Text":"TEAR","DrawingId":"tear","Value":"","SortValue":"","Drawing":"13E","Kind":"Noun","Category":"Body","PlaySessionLink":"","Tags":"","Complexity":"4","Gender":"","Form":"","Article":"","LinkedWord":"","Notes":"","Spanish":"LÁGRIMA","Italian":"LACRIMA"},{"Id":"television","Active":"1","Text":"TELEVISION","DrawingId":"television","Value":"","SortValue":"","Drawing":"A5","Kind":"Noun","Category":"Home","PlaySessionLink":"","Tags":"","Complexity":"10","Gender":"","Form":"","Article":"","LinkedWord":"","Notes":"","Spanish":"TELEVISIÓN","Italian":"TELEVISIONE"},{"Id":"test","Active":"1","Text":"TEST","DrawingId":"test","Value":"","SortValue":"","Drawing":"13C","Kind":"Noun","Category":"Objects","PlaySessionLink":"","Tags":"","Complexity":"4","Gender":"","Form":"","Article":"","LinkedWord":"","Notes":"","Spanish":"EXAMEN","Italian":"ESAME"},{"Id":"theatre","Active":"1","Text":"THEATRE","DrawingId":"theatre","Value":"","SortValue":"","Drawing":"130","Kind":"Noun","Category":"City","PlaySessionLink":"","Tags":"","Complexity":"7","Gender":"","Form":"","Article":"","LinkedWord":"","Notes":"","Spanish":"TEATRO","Italian":"TEATRO"},{"Id":"tiger","Active":"1","Text":"TIGER","DrawingId":"tiger","Value":"","SortValue":"","Drawing":"F5","Kind":"Noun","Category":"Animals","PlaySessionLink":"","Tags":"","Complexity":"5","Gender":"","Form":"","Article":"","LinkedWord":"","Notes":"","Spanish":"TIGRE","Italian":"TIGRE"},{"Id":"toilet","Active":"1","Text":"TOILET","DrawingId":"toilet","Value":"","SortValue":"","Drawing":"153","Kind":"Noun","Category":"Home","PlaySessionLink":"","Tags":"","Complexity":"6","Gender":"","Form":"","Article":"","LinkedWord":"","Notes":"","Spanish":"BAÑO","Italian":"GABINETTO"},{"Id":"tomato","Active":"1","Text":"TOMATO","DrawingId":"tomato","Value":"","SortValue":"","Drawing":"FE","Kind":"Noun","Category":"Food","PlaySessionLink":"","Tags":"","Complexity":"6","Gender":"","Form":"","Article":"","LinkedWord":"","Notes":"","Spanish":"TOMATE","Italian":"POMODORO"},{"Id":"tongue","Active":"1","Text":"TONGUE","DrawingId":"tongue","Value":"","SortValue":"","Drawing":"118","Kind":"Noun","Category":"Body","PlaySessionLink":"","Tags":"","Complexity":"6","Gender":"","Form":"","Article":"","LinkedWord":"","Notes":"","Spanish":"LENGUA","Italian":"LINGUA"},{"Id":"tooth","Active":"1","Text":"TOOTH","DrawingId":"tooth","Value":"","SortValue":"","Drawing":"DF","Kind":"Noun","Category":"Body","PlaySessionLink":"","Tags":"","Complexity":"5","Gender":"","Form":"","Article":"","LinkedWord":"","Notes":"","Spanish":"DIENTE","Italian":"DENTE"},{"Id":"towel","Active":"1","Text":"TOWEL","DrawingId":"towel","Value":"","SortValue":"","Drawing":"218","Kind":"Noun","Category":"Home","PlaySessionLink":"","Tags":"","Complexity":"5","Gender":"","Form":"","Article":"","LinkedWord":"","Notes":"","Spanish":"TOALLA","Italian":"ASCIUGAMANO"},{"Id":"town","Active":"1","Text":"TOWN","DrawingId":"town","Value":"","SortValue":"","Drawing":"219","Kind":"Noun","Category":"City","PlaySessionLink":"","Tags":"","Complexity":"4","Gender":"","Form":"","Article":"","LinkedWord":"","Notes":"","Spanish":"PUEBLO","Italian":"CITTADINA"},{"Id":"toy","Active":"1","Text":"TOY","DrawingId":"toy","Value":"","SortValue":"","Drawing":"142","Kind":"Noun","Category":"Objects","PlaySessionLink":"","Tags":"","Complexity":"3","Gender":"","Form":"","Article":"","LinkedWord":"","Notes":"","Spanish":"JUGUETE","Italian":"GIOCATTOLO"},{"Id":"train","Active":"1","Text":"TRAIN","DrawingId":"train","Value":"","SortValue":"","Drawing":"021A","Kind":"Noun","Category":"City","PlaySessionLink":"","Tags":"","Complexity":"5","Gender":"","Form":"","Article":"","LinkedWord":"","Notes":"","Spanish":"TREN","Italian":"TRENO"},{"Id":"tree","Active":"1","Text":"TREE","DrawingId":"tree","Value":"","SortValue":"","Drawing":"FB","Kind":"Noun","Category":"Nature","PlaySessionLink":"","Tags":"","Complexity":"4","Gender":"","Form":"","Article":"","LinkedWord":"","Notes":"","Spanish":"ÁRBOL","Italian":"ALBERO"},{"Id":"trousers","Active":"1","Text":"TROUSERS","DrawingId":"trousers","Value":"","SortValue":"","Drawing":"F8","Kind":"Noun","Category":"Clothes","PlaySessionLink":"","Tags":"","Complexity":"8","Gender":"","Form":"","Article":"","LinkedWord":"","Notes":"","Spanish":"PANTALONES","Italian":"PANTALONI"},{"Id":"truck","Active":"1","Text":"TRUCK","DrawingId":"truck","Value":"","SortValue":"","Drawing":"144","Kind":"Noun","Category":"City","PlaySessionLink":"","Tags":"","Complexity":"5","Gender":"","Form":"","Article":"","LinkedWord":"","Notes":"","Spanish":"CAMIÓN","Italian":"CAMION"},{"Id":"turtle","Active":"1","Text":"TURTLE","DrawingId":"turtle","Value":"","SortValue":"","Drawing":"021B","Kind":"Noun","Category":"Animals","PlaySessionLink":"","Tags":"","Complexity":"6","Gender":"","Form":"","Article":"","LinkedWord":"","Notes":"","Spanish":"TORTUGA","Italian":"TARTARUGA"},{"Id":"uncle","Active":"1","Text":"UNCLE","DrawingId":"uncle","Value":"","SortValue":"","Drawing":"A2","Kind":"Noun","Category":"Family","PlaySessionLink":"","Tags":"","Complexity":"5","Gender":"","Form":"","Article":"","LinkedWord":"","Notes":"","Spanish":"TÍO","Italian":"ZIO"},{"Id":"volcano","Active":"1","Text":"VOLCANO","DrawingId":"volcano","Value":"","SortValue":"","Drawing":"1EA6","Kind":"Noun","Category":"Nature","PlaySessionLink":"","Tags":"","Complexity":"7","Gender":"","Form":"","Article":"","LinkedWord":"","Notes":"","Spanish":"VOLCÁN","Italian":"VULCANO"},{"Id":"washing_machine","Active":"0","Text":"WASHING-MACHINE","DrawingId":"washing_machine","Value":"","SortValue":"","Drawing":"175","Kind":"Noun","Category":"Home","PlaySessionLink":"","Tags":"","Complexity":"","Gender":"","Form":"","Article":"","LinkedWord":"","Notes":"","Spanish":"LAVADORA","Italian":""},{"Id":"water","Active":"1","Text":"WATER","DrawingId":"water","Value":"","SortValue":"","Drawing":"2019","Kind":"Noun","Category":"Food","PlaySessionLink":"","Tags":"","Complexity":"5","Gender":"","Form":"","Article":"","LinkedWord":"","Notes":"","Spanish":"AGUA","Italian":"ACQUA"},{"Id":"watermelon","Active":"1","Text":"WATERMELON","DrawingId":"watermelon","Value":"","SortValue":"","Drawing":"3F","Kind":"Noun","Category":"Food","PlaySessionLink":"","Tags":"","Complexity":"10","Gender":"","Form":"","Article":"","LinkedWord":"","Notes":"","Spanish":"SANDÍA","Italian":"ANGURIA"},{"Id":"whale","Active":"1","Text":"WHALE","DrawingId":"whale","Value":"","SortValue":"","Drawing":"FD","Kind":"Noun","Category":"Animals","PlaySessionLink":"","Tags":"","Complexity":"5","Gender":"","Form":"Singular","Article":"","LinkedWord":"","Notes":"","Spanish":"BALLENA","Italian":"BALENA"},{"Id":"window","Active":"1","Text":"WINDOW","DrawingId":"window","Value":"","SortValue":"","Drawing":"177","Kind":"Noun","Category":"Home","PlaySessionLink":"","Tags":"","Complexity":"6","Gender":"","Form":"","Article":"","LinkedWord":"","Notes":"","Spanish":"VENTANA","Italian":"FINESTRA"},{"Id":"winter","Active":"1","Text":"WINTER","DrawingId":"winter","Value":"4","SortValue":"4","Drawing":"BF","Kind":"Noun","Category":"Seasons","PlaySessionLink":"","Tags":"","Complexity":"6","Gender":"","Form":"","Article":"","LinkedWord":"","Notes":"","Spanish":"INVIERNO","Italian":"INVERNO"},{"Id":"woman","Active":"1","Text":"WOMAN","DrawingId":"woman","Value":"","SortValue":"","Drawing":"22","Kind":"Noun","Category":"Family","PlaySessionLink":"","Tags":"","Complexity":"5","Gender":"","Form":"","Article":"","LinkedWord":"","Notes":"","Spanish":"MUJER","Italian":"DONNA"},{"Id":"yogurt","Active":"1","Text":"YOGHURT","DrawingId":"yogurt","Value":"","SortValue":"","Drawing":"2A","Kind":"Noun","Category":"Food","PlaySessionLink":"","Tags":"","Complexity":"7","Gender":"","Form":"","Article":"","LinkedWord":"","Notes":"","Spanish":"YOGUR","Italian":"YOGURT"},{"Id":"zoo","Active":"1","Text":"ZOO","DrawingId":"zoo","Value":"","SortValue":"","Drawing":"148","Kind":"Noun","Category":"City","PlaySessionLink":"","Tags":"","Complexity":"3","Gender":"","Form":"","Article":"","LinkedWord":"","Notes":"","Spanish":"ZOOLÓGICO","Italian":"ZOO"}]}