{
  "version": "1",
  "cardId": "number_2",
  "lines": [
    {
      "key": "number_2",
      "lang": "ar",
      "sourceText": "رقم 2",
      "audioFile": "number_2.ar.mp3",
      "voiceProfile": "haytham",
      "actorId": "Default",
      "durationMs": 810,
      "updatedAt": "2026-04-12T00:08:06Z",
      "textHash": "54aa0288fd4c623df633aff5daccc63b80a3ad7f83438ca11fd33718750b3295"
    },
    {
      "key": "number_2",
      "lang": "de",
      "sourceText": "Nummer 2",
      "audioFile": "number_2.de.mp3",
      "voiceProfile": "alice",
      "actorId": "Default",
      "durationMs": 1123,
      "updatedAt": "2026-04-12T00:08:07Z",
      "textHash": "b835b8c22978a6fd48e1160286e0a33f657732aa2c0ae3fcf6164e249f95f59b"
    },
    {
      "key": "number_2",
      "lang": "en",
      "sourceText": "Number 2",
      "audioFile": "number_2.en.mp3",
      "voiceProfile": "alex",
      "actorId": "Default",
      "durationMs": 810,
      "updatedAt": "2026-04-12T00:08:08Z",
      "textHash": "5bf96f7ed05c910e20f4a8b7a1223437f54128cc85f69e57c035c730e49fe0e3"
    },
    {
      "key": "number_2",
      "lang": "es",
      "sourceText": "Número 2",
      "audioFile": "number_2.es.mp3",
      "voiceProfile": "ninoska",
      "actorId": "Default",
      "durationMs": 940,
      "updatedAt": "2026-04-12T00:08:08Z",
      "textHash": "30a886fd7f81beed0e94bc0746f8b4c16af5ddb7d4fd780cf901dc48ec5ceaef"
    },
    {
      "key": "number_2",
      "lang": "fr",
      "sourceText": "Numéro 2",
      "audioFile": "number_2.fr.mp3",
      "voiceProfile": "clement_fr",
      "actorId": "Default",
      "durationMs": 810,
      "updatedAt": "2026-04-12T00:08:09Z",
      "textHash": "9d9b2c880249a84de1ee68a03c76facd2a2b49797a7770972e207a5cd23d43f1"
    },
    {
      "key": "number_2",
      "lang": "hu",
      "sourceText": "2. szám",
      "audioFile": "number_2.hu.mp3",
      "voiceProfile": "shelley",
      "actorId": "Default",
      "durationMs": 888,
      "updatedAt": "2026-04-12T00:08:10Z",
      "textHash": "c7c0e370d423329efd2845af46a2b30aa4dcdf0ca47b3c504a7fae4a0bfcbfaa"
    },
    {
      "key": "number_2",
      "lang": "it",
      "sourceText": "Numero 2",
      "audioFile": "number_2.it.mp3",
      "voiceProfile": "francesco",
      "actorId": "Default",
      "durationMs": 810,
      "updatedAt": "2026-04-12T00:08:11Z",
      "textHash": "2a573bdea393df1fa904755a1c3e096759ba4c11848f166053999d0aaf8c8b1c"
    },
    {
      "key": "number_2",
      "lang": "pl",
      "sourceText": "Cyfra 2",
      "audioFile": "number_2.pl.mp3",
      "voiceProfile": "alice",
      "actorId": "Default",
      "durationMs": 1176,
      "updatedAt": "2026-04-12T00:08:12Z",
      "textHash": "054e954f94886b373f023fc08514fdf35afeba7730dcb09edda551274520f234"
    },
    {
      "key": "number_2",
      "lang": "ro",
      "sourceText": "Numărul 2",
      "audioFile": "number_2.ro.mp3",
      "voiceProfile": "cristi",
      "actorId": "Default",
      "durationMs": 862,
      "updatedAt": "2026-04-12T00:08:13Z",
      "textHash": "3a4454461d134f6b74b7b88c7fbc7a35e8a9834f18ccd66b7a868eaeff0dee47"
    },
    {
      "key": "number_2",
      "lang": "ru",
      "sourceText": "Номер 2",
      "audioFile": "number_2.ru.mp3",
      "voiceProfile": "felix",
      "actorId": "Default",
      "durationMs": 758,
      "updatedAt": "2026-04-12T00:08:13Z",
      "textHash": "8af9549eb641d4d543ffc412a493ecd2cd4531f6ce260888c615c6bd73553101"
    },
    {
      "key": "number_2",
      "lang": "uk",
      "sourceText": "Номер 2",
      "audioFile": "number_2.uk.mp3",
      "voiceProfile": "yaroslava",
      "actorId": "Default",
      "durationMs": 1097,
      "updatedAt": "2026-04-12T00:08:14Z",
      "textHash": "d551843cdd49afb9c1e5299324df7bd4dd21d4c671a6168948de959536162f2d"
    }
  ]
}