{
  "version": "1",
  "cardId": "bike",
  "lines": [
    {
      "key": "bike",
      "lang": "ar",
      "sourceText": "دراجة",
      "audioFile": "bike.ar.mp3",
      "voiceProfile": "haytham",
      "actorId": "Default",
      "durationMs": 810,
      "updatedAt": "2026-04-11T23:27:18Z",
      "textHash": "e9585c4ee62da257aa7e4f498d8997ca6c090f53af5e6a8c21c28d79a3fa8e80"
    },
    {
      "key": "bike",
      "lang": "de",
      "sourceText": "Fahrrad",
      "audioFile": "bike.de.mp3",
      "voiceProfile": "alice",
      "actorId": "Default",
      "durationMs": 993,
      "updatedAt": "2026-04-11T23:27:19Z",
      "textHash": "246f5e02f2ff0cdc61331826746f2956f35ad322f25774ccac5496251225522e"
    },
    {
      "key": "bike",
      "lang": "en",
      "sourceText": "Bike",
      "audioFile": "bike.en.mp3",
      "voiceProfile": "alex",
      "actorId": "Default",
      "durationMs": 679,
      "updatedAt": "2026-04-11T23:27:20Z",
      "textHash": "24680094ec500d124fda77de7e81924a5f7b70ba68c4771251c4f4c12f6021f5"
    },
    {
      "key": "bike",
      "lang": "es",
      "sourceText": "Bicicleta",
      "audioFile": "bike.es.mp3",
      "voiceProfile": "ninoska",
      "actorId": "Default",
      "durationMs": 1123,
      "updatedAt": "2026-04-11T23:27:21Z",
      "textHash": "86ea870ce00eb14dc738a52e4c01602ba21fd11807596671bd6952f0ed66d12e"
    },
    {
      "key": "bike",
      "lang": "fr",
      "sourceText": "Vélo",
      "audioFile": "bike.fr.mp3",
      "voiceProfile": "clement_fr",
      "actorId": "Default",
      "durationMs": 575,
      "updatedAt": "2026-04-11T23:27:22Z",
      "textHash": "70900e74b91241d8263628a965e0ea9fd869d2389f161e5bf489d7cc378a5e2b"
    },
    {
      "key": "bike",
      "lang": "hu",
      "sourceText": "Bicikli",
      "audioFile": "bike.hu.mp3",
      "voiceProfile": "shelley",
      "actorId": "Default",
      "durationMs": 810,
      "updatedAt": "2026-04-11T23:27:23Z",
      "textHash": "41fcf7952e4b3d97ab97e22b4ae721f4ec87ba3fd7b61dcdaebac5de50b50909"
    },
    {
      "key": "bike",
      "lang": "it",
      "sourceText": "Bicicletta",
      "audioFile": "bike.it.mp3",
      "voiceProfile": "francesco",
      "actorId": "Default",
      "durationMs": 888,
      "updatedAt": "2026-04-11T23:27:24Z",
      "textHash": "15696ab28a142b4d75f988fa398330586856847d93e1c4d9e56e06833c94ce32"
    },
    {
      "key": "bike",
      "lang": "pl",
      "sourceText": "Rower",
      "audioFile": "bike.pl.mp3",
      "voiceProfile": "alice",
      "actorId": "Default",
      "durationMs": 758,
      "updatedAt": "2026-04-11T23:27:25Z",
      "textHash": "ed90ab8f3f8cc6da0344b8463178827ee8c7bbe51a90c4ddc2aaa84f8f30832f"
    },
    {
      "key": "bike",
      "lang": "ro",
      "sourceText": "bicicleta",
      "audioFile": "bike.ro.mp3",
      "voiceProfile": "cristi",
      "actorId": "Default",
      "durationMs": 888,
      "updatedAt": "2026-04-11T23:27:26Z",
      "textHash": "f916e81f44ff8388bc987c7acbba5b71b3bc4c43f5bf960a6bb3e848af6537e8"
    },
    {
      "key": "bike",
      "lang": "ru",
      "sourceText": "Велосипед",
      "audioFile": "bike.ru.mp3",
      "voiceProfile": "felix",
      "actorId": "Default",
      "durationMs": 888,
      "updatedAt": "2026-04-11T23:27:27Z",
      "textHash": "b7b1b70e953e993e67284924cce06c76dfa6308a63a83a405f300ebc58698de4"
    },
    {
      "key": "bike",
      "lang": "uk",
      "sourceText": "велосипед",
      "audioFile": "bike.uk.mp3",
      "voiceProfile": "yaroslava",
      "actorId": "Default",
      "durationMs": 993,
      "updatedAt": "2026-04-11T23:27:28Z",
      "textHash": "9874e45142a9b5ba9c51f064273831fd6959ab0e2377c602b2b0e21b64f01ac8"
    }
  ]
}