{
  "version": "1",
  "cardId": "vistula_river",
  "lines": [
    {
      "key": "vistula_river",
      "lang": "ar",
      "sourceText": "نهر فيستولا",
      "audioFile": "vistula_river.ar.mp3",
      "voiceProfile": "haytham",
      "actorId": "Default",
      "durationMs": 1280,
      "updatedAt": "2026-04-12T00:23:42Z",
      "textHash": "3668bdd8b1c3a2baa6041200bce2137f32017f560e78f5ff0799a7be6cf596ed"
    },
    {
      "key": "vistula_river",
      "lang": "de",
      "sourceText": "Weichsel",
      "audioFile": "vistula_river.de.mp3",
      "voiceProfile": "alice",
      "actorId": "Default",
      "durationMs": 1045,
      "updatedAt": "2026-04-12T00:23:44Z",
      "textHash": "29d6ccb665f9d269ad87d7ec8a980974ba009b46b36204f3981fca829aec40a5"
    },
    {
      "key": "vistula_river",
      "lang": "en",
      "sourceText": "Vistula River",
      "audioFile": "vistula_river.en.mp3",
      "voiceProfile": "alex",
      "actorId": "Default",
      "durationMs": 1123,
      "updatedAt": "2026-04-12T00:23:44Z",
      "textHash": "ffd779a7349f00fdd138c8706b94e3eeb658803553916be605f3e2850d5bcbb6"
    },
    {
      "key": "vistula_river",
      "lang": "es",
      "sourceText": "Río Vístula",
      "audioFile": "vistula_river.es.mp3",
      "voiceProfile": "ninoska",
      "actorId": "Default",
      "durationMs": 1228,
      "updatedAt": "2026-04-12T00:23:45Z",
      "textHash": "0480011d9ee38bfaa9df8a6ee780d7dfea437090250930b724e7f20fec57dde3"
    },
    {
      "key": "vistula_river",
      "lang": "fr",
      "sourceText": "la Vistule",
      "audioFile": "vistula_river.fr.mp3",
      "voiceProfile": "clement_fr",
      "actorId": "Default",
      "durationMs": 888,
      "updatedAt": "2026-04-12T00:23:46Z",
      "textHash": "0e17445cd5d6f3e8f73007d8646121bd6088cb7fc77f518ed7e9890db0eafaf7"
    },
    {
      "key": "vistula_river",
      "lang": "hu",
      "sourceText": "Visztula folyó",
      "audioFile": "vistula_river.hu.mp3",
      "voiceProfile": "shelley",
      "actorId": "Default",
      "durationMs": 1045,
      "updatedAt": "2026-04-12T00:23:47Z",
      "textHash": "0bfa06a5fff68890cb4038eec0bf5f6a94350c7790e402e3573f9c9eac752cd5"
    },
    {
      "key": "vistula_river",
      "lang": "it",
      "sourceText": "fiume Vistola",
      "audioFile": "vistula_river.it.mp3",
      "voiceProfile": "francesco",
      "actorId": "Default",
      "durationMs": 993,
      "updatedAt": "2026-04-12T00:23:48Z",
      "textHash": "490f882b516ee27ae9d523854b368fba29425b78dc343ad16d48514db03ce315"
    },
    {
      "key": "vistula_river",
      "lang": "pl",
      "sourceText": "Wisła",
      "audioFile": "vistula_river.pl.mp3",
      "voiceProfile": "alice",
      "actorId": "Default",
      "durationMs": 1097,
      "updatedAt": "2026-04-12T00:23:50Z",
      "textHash": "5322722dcacd75f0be9cc5d22927637a1f905759e136611f572dc0580e170a9a"
    },
    {
      "key": "vistula_river",
      "lang": "ro",
      "sourceText": "Râul Vistula",
      "audioFile": "vistula_river.ro.mp3",
      "voiceProfile": "cristi",
      "actorId": "Default",
      "durationMs": 1045,
      "updatedAt": "2026-04-12T00:23:50Z",
      "textHash": "89678807947d7b3679aba542ca5a15cbfc55e995f4e52295f8d9220a716a4f7c"
    },
    {
      "key": "vistula_river",
      "lang": "ru",
      "sourceText": "Река Висла",
      "audioFile": "vistula_river.ru.mp3",
      "voiceProfile": "felix",
      "actorId": "Default",
      "durationMs": 888,
      "updatedAt": "2026-04-12T00:23:51Z",
      "textHash": "cc3e2696d89355f6e7fe6e443c2c6978820d46d455d25dd8491d7372728e7007"
    },
    {
      "key": "vistula_river",
      "lang": "uk",
      "sourceText": "Річка Вісла",
      "audioFile": "vistula_river.uk.mp3",
      "voiceProfile": "yaroslava",
      "actorId": "Default",
      "durationMs": 1176,
      "updatedAt": "2026-04-12T00:23:52Z",
      "textHash": "0fb4ec5a24984442d9889b34cef53312a4449ac7273c44a7d45e7ac64c2631a7"
    }
  ]
}