{
  "version": "1",
  "cardId": "chopin_monument",
  "lines": [
    {
      "key": "chopin_monument",
      "lang": "ar",
      "sourceText": "نصب شوبان التذكاري",
      "audioFile": "chopin_monument.ar.mp3",
      "voiceProfile": "haytham",
      "actorId": "Default",
      "durationMs": 1829,
      "updatedAt": "2026-04-11T23:34:47Z",
      "textHash": "b50b229709efd7562384e0ad7cd94b371d661a7bb48a0cfadf3d720fb9a1c62e"
    },
    {
      "key": "chopin_monument",
      "lang": "de",
      "sourceText": "Chopin-Denkmal",
      "audioFile": "chopin_monument.de.mp3",
      "voiceProfile": "alice",
      "actorId": "Default",
      "durationMs": 1280,
      "updatedAt": "2026-04-11T23:34:49Z",
      "textHash": "d0daaf4895ff6d325c26ade65130ebd4fd09382e76f263c0f2050ceac5aefe0c"
    },
    {
      "key": "chopin_monument",
      "lang": "en",
      "sourceText": "Chopin Monument",
      "audioFile": "chopin_monument.en.mp3",
      "voiceProfile": "alex",
      "actorId": "Default",
      "durationMs": 1280,
      "updatedAt": "2026-04-11T23:34:49Z",
      "textHash": "62922379e94009106dc81d7ace805ad7e610704cb908de4edcbf75d036d1cdbd"
    },
    {
      "key": "chopin_monument",
      "lang": "es",
      "sourceText": "Monumento a Chopin",
      "audioFile": "chopin_monument.es.mp3",
      "voiceProfile": "ninoska",
      "actorId": "Default",
      "durationMs": 1593,
      "updatedAt": "2026-04-11T23:34:50Z",
      "textHash": "c11c145d69e427f0d3203e1daeff8d7258fab45904ce879c045fd482f9bcbd45"
    },
    {
      "key": "chopin_monument",
      "lang": "fr",
      "sourceText": "Monument à Chopin",
      "audioFile": "chopin_monument.fr.mp3",
      "voiceProfile": "clement_fr",
      "actorId": "Default",
      "durationMs": 1097,
      "updatedAt": "2026-04-11T23:34:51Z",
      "textHash": "13e129b3a36e8e076d816c41ded757aa2ba4ac0c3cdbfd8c62961681afc045bb"
    },
    {
      "key": "chopin_monument",
      "lang": "hu",
      "sourceText": "Chopin-emlékmű",
      "audioFile": "chopin_monument.hu.mp3",
      "voiceProfile": "shelley",
      "actorId": "Default",
      "durationMs": 1541,
      "updatedAt": "2026-04-11T23:34:52Z",
      "textHash": "7d1849fc3ff0742962913e17d1d201cf19a7f3b558d2c51cb6e8c92a02f09f15"
    },
    {
      "key": "chopin_monument",
      "lang": "it",
      "sourceText": "Monumento a Chopin",
      "audioFile": "chopin_monument.it.mp3",
      "voiceProfile": "francesco",
      "actorId": "Default",
      "durationMs": 1123,
      "updatedAt": "2026-04-11T23:34:53Z",
      "textHash": "25e1583ab6310a0a21c62ad550315b59e41bfe47788d28139b6823b127c1af6f"
    },
    {
      "key": "chopin_monument",
      "lang": "pl",
      "sourceText": "Pomnik Chopina",
      "audioFile": "chopin_monument.pl.mp3",
      "voiceProfile": "alice",
      "actorId": "Default",
      "durationMs": 1228,
      "updatedAt": "2026-04-11T23:34:54Z",
      "textHash": "ed85d1bb90bd33b74a9a848f4000189ffda8ab28e063736549abbb6a792d5ce4"
    },
    {
      "key": "chopin_monument",
      "lang": "ro",
      "sourceText": "Monumentul Chopin",
      "audioFile": "chopin_monument.ro.mp3",
      "voiceProfile": "cristi",
      "actorId": "Default",
      "durationMs": 1306,
      "updatedAt": "2026-04-11T23:34:55Z",
      "textHash": "43d27d6dceab1188e27db9bfa28482732069544a3e20235a2e4e3981c486299c"
    },
    {
      "key": "chopin_monument",
      "lang": "ru",
      "sourceText": "Памятник Шопену",
      "audioFile": "chopin_monument.ru.mp3",
      "voiceProfile": "felix",
      "actorId": "Default",
      "durationMs": 1280,
      "updatedAt": "2026-04-11T23:34:56Z",
      "textHash": "181c9f399e958ecf203ebb3e4846ddf0550d81abbba27c7263fc13614b7a2e38"
    },
    {
      "key": "chopin_monument",
      "lang": "uk",
      "sourceText": "Пам'ятник Шопену",
      "audioFile": "chopin_monument.uk.mp3",
      "voiceProfile": "yaroslava",
      "actorId": "Default",
      "durationMs": 1593,
      "updatedAt": "2026-04-11T23:34:57Z",
      "textHash": "7daa16ff6d6aff4d5ab415df4af40e75e2dfa212079863b7c4a9d2502e128d3c"
    }
  ]
}