{
  "version": "1",
  "cardId": "planetarium",
  "lines": [
    {
      "key": "planetarium",
      "lang": "ar",
      "sourceText": "القبة السماوية",
      "audioFile": "planetarium.ar.mp3",
      "voiceProfile": "haytham",
      "actorId": "Default",
      "durationMs": 1541,
      "updatedAt": "2026-04-12T00:13:34Z",
      "textHash": "5e9aeae7ea7d8daa0d3583595844418649549783b62033d19fbdaf546f5aec85"
    },
    {
      "key": "planetarium",
      "lang": "de",
      "sourceText": "Planetarium",
      "audioFile": "planetarium.de.mp3",
      "voiceProfile": "alice",
      "actorId": "Default",
      "durationMs": 1123,
      "updatedAt": "2026-04-12T00:13:36Z",
      "textHash": "a25911282edb4f67e1c46a0225dfb2796f6b9db776e5c937b46b2bea1f662a33"
    },
    {
      "key": "planetarium",
      "lang": "en",
      "sourceText": "Planetarium",
      "audioFile": "planetarium.en.mp3",
      "voiceProfile": "alex",
      "actorId": "Default",
      "durationMs": 1123,
      "updatedAt": "2026-04-12T00:13:37Z",
      "textHash": "49b4c48a243bfea8ac8114399a5ce0e77c8d3b9a3ed5356e750ff78fff4756f5"
    },
    {
      "key": "planetarium",
      "lang": "es",
      "sourceText": "Planetario",
      "audioFile": "planetarium.es.mp3",
      "voiceProfile": "ninoska",
      "actorId": "Default",
      "durationMs": 1228,
      "updatedAt": "2026-04-12T00:13:38Z",
      "textHash": "62bdf84f8d8394fcb9970a5a803eecc7f01a362442a0a2474021626d91aabfac"
    },
    {
      "key": "planetarium",
      "lang": "fr",
      "sourceText": "Planétarium",
      "audioFile": "planetarium.fr.mp3",
      "voiceProfile": "clement_fr",
      "actorId": "Default",
      "durationMs": 888,
      "updatedAt": "2026-04-12T00:13:39Z",
      "textHash": "9bc087844056689e78f9ee710360ae32536aaa8ab0452d9d886b81c6fe42f03d"
    },
    {
      "key": "planetarium",
      "lang": "hu",
      "sourceText": "Planetárium",
      "audioFile": "planetarium.hu.mp3",
      "voiceProfile": "shelley",
      "actorId": "Default",
      "durationMs": 1228,
      "updatedAt": "2026-04-12T00:13:40Z",
      "textHash": "b07b2a7e55791b488e4a41488beb33ae3fffb31f01acac006da4725e808192c5"
    },
    {
      "key": "planetarium",
      "lang": "it",
      "sourceText": "Planetario",
      "audioFile": "planetarium.it.mp3",
      "voiceProfile": "francesco",
      "actorId": "Default",
      "durationMs": 888,
      "updatedAt": "2026-04-12T00:13:41Z",
      "textHash": "4e2903f1b9a61dee2ce780200285ae702600d62a81f576f88d0e94a2cd640867"
    },
    {
      "key": "planetarium",
      "lang": "pl",
      "sourceText": "Planetarium",
      "audioFile": "planetarium.pl.mp3",
      "voiceProfile": "alice",
      "actorId": "Default",
      "durationMs": 1097,
      "updatedAt": "2026-04-12T00:13:42Z",
      "textHash": "4ef7f5c00295c26876f49c00f46a2b60891a0e42e94749917ff5f01779c11da7"
    },
    {
      "key": "planetarium",
      "lang": "ro",
      "sourceText": "Planetariu",
      "audioFile": "planetarium.ro.mp3",
      "voiceProfile": "cristi",
      "actorId": "Default",
      "durationMs": 993,
      "updatedAt": "2026-04-12T00:13:43Z",
      "textHash": "0873c193cbcc976595057afd5b87463e8bdf9040af46c3f4d6abf744f4b9d703"
    },
    {
      "key": "planetarium",
      "lang": "ru",
      "sourceText": "Планетарий",
      "audioFile": "planetarium.ru.mp3",
      "voiceProfile": "felix",
      "actorId": "Default",
      "durationMs": 862,
      "updatedAt": "2026-04-12T00:13:44Z",
      "textHash": "4cbcb9f056c8ec083dbc31fe9b4a232452abf35ed0a7809aee8a70d35f3f981b"
    },
    {
      "key": "planetarium",
      "lang": "uk",
      "sourceText": "Планетарій",
      "audioFile": "planetarium.uk.mp3",
      "voiceProfile": "yaroslava",
      "actorId": "Default",
      "durationMs": 1045,
      "updatedAt": "2026-04-12T00:13:45Z",
      "textHash": "7ab7479a2644bac916b91657f729a1c841e299b38cb8ed58c82da33685172c88"
    }
  ]
}